<?xml version="1.0" encoding="UTF-8"?>
<Index xmlns="http://www.tso.co.uk/assets/namespace/gazetteindex" editionCode="L" page="053" pageID="https://www.thegazette.co.uk/id/London/index/year/1923/volume/2/page/053" pagePDF="https://www.thegazette.co.uk/London/index/year/1923/volume/2/page/053" pageRDF="https://www.thegazette.co.uk/London/index/year/1923/volume/2/page/053?view=linked-data" type="index" volume="2" year="1923">
  <ItemGroup>
    <MainItem>
      <Key>Bock</Key>
      <Forenames>C. C.</Forenames>
      <PageNumber>2561</PageNumber>
    </MainItem>
  </ItemGroup>
  <ItemGroup>
    <MainItem>
      <Key>Bodley</Key>
      <Forenames>L. O .</Forenames>
      <PageNumber>3630</PageNumber>
    </MainItem>
  </ItemGroup>
  <ItemGroup>
    <MainItem>
      <Key>Borwick</Key>
      <Forenames>B. H.</Forenames>
      <PageNumber>3223</PageNumber>
    </MainItem>
  </ItemGroup>
  <ItemGroup>
    <MainItem>
      <Key>Bostock</Key>
      <Forenames>J. A.</Forenames>
      <PageNumber>2569</PageNumber>
    </MainItem>
  </ItemGroup>
  <ItemGroup>
    <MainItem>
      <Key>Bourdillon</Key>
      <Forenames>F. H.</Forenames>
      <PageNumber>2569</PageNumber>
    </MainItem>
  </ItemGroup>
  <ItemGroup>
    <MainItem>
      <Key>Bowden</Key>
      <Forenames>S. A.</Forenames>
      <PageNumber>4212</PageNumber>
    </MainItem>
  </ItemGroup>
  <ItemGroup>
    <MainItem>
      <Key>Bowe</Key>
      <Forenames>R. W.</Forenames>
      <PageNumber>2731</PageNumber>
    </MainItem>
  </ItemGroup>
  <ItemGroup>
    <MainItem>
      <Key>Bowers</Key>
      <Forenames>P. L.</Forenames>
      <PageNumber>3872</PageNumber>
    </MainItem>
  </ItemGroup>
  <ItemGroup>
    <MainItem>
      <Key>Boyd</Key>
      <Forenames>H. S .</Forenames>
      <PageNumber>2731</PageNumber>
    </MainItem>
  </ItemGroup>
  <ItemGroup>
    <MainItem>
      <Key>Brackenbury</Key>
      <Forenames>W. J. W.</Forenames>
      <PageNumber>3872</PageNumber>
    </MainItem>
  </ItemGroup>
  <ItemGroup>
    <MainItem>
      <Key>Brannon</Key>
      <Forenames>A. C. P.</Forenames>
      <PageNumber>2569</PageNumber>
    </MainItem>
  </ItemGroup>
  <ItemGroup>
    <MainItem>
      <Key>Brayley</Key>
      <Forenames>C. E. W.</Forenames>
      <PageNumber>2731</PageNumber>
    </MainItem>
  </ItemGroup>
  <ItemGroup>
    <MainItem>
      <Key>Bree</Key>
      <Forenames>P. G.</Forenames>
      <PageNumber>3223</PageNumber>
    </MainItem>
  </ItemGroup>
  <ItemGroup>
    <MainItem>
      <Key>Brett</Key>
      <Forenames>E. T. St</Forenames>
      <Text>. M</Text>
      <PageNumber>2569</PageNumber>
    </MainItem>
  </ItemGroup>
  <ItemGroup>
    <MainItem>
      <Key>Brigham</Key>
      <Forenames>G.</Forenames>
      <PageNumber>2731</PageNumber>
    </MainItem>
  </ItemGroup>
  <ItemGroup>
    <MainItem>
      <Key>Britts</Key>
      <Forenames>M. H. J .</Forenames>
      <PageNumber>3223</PageNumber>
    </MainItem>
  </ItemGroup>
  <ItemGroup>
    <MainItem>
      <Key>Brooke</Key>
      <Forenames>L. H.</Forenames>
      <PageNumber>3068</PageNumber>
    </MainItem>
  </ItemGroup>
  <ItemGroup>
    <MainItem>
      <Key>Brown</Key>
      <Forenames>A. D.</Forenames>
      <PageNumber>3871</PageNumber>
    </MainItem>
  </ItemGroup>
  <ItemGroup>
    <MainItem>
      <Key>
        <KeyDitto>___ ___ ___ ___</KeyDitto>
      </Key>
      <Forenames>C. A .</Forenames>
      <PageNumber>3067</PageNumber>
    </MainItem>
  </ItemGroup>
  <ItemGroup>
    <MainItem>
      <Key>
        <KeyDitto>___ ___ ___ ___</KeyDitto>
      </Key>
      <Forenames>James</Forenames>
      <PageNumber>2569</PageNumber>
    </MainItem>
  </ItemGroup>
  <ItemGroup>
    <MainItem>
      <Key>
        <KeyDitto>___ ___ ___</KeyDitto>
      </Key>
      <Title>John .</Title>
      <PageNumber>2569</PageNumber>
    </MainItem>
  </ItemGroup>
  <ItemGroup>
    <MainItem>
      <Key>
        <KeyDitto>___ ___ ___ ___</KeyDitto>
      </Key>
      <Forenames>M. A .</Forenames>
      <PageNumber>2569</PageNumber>
    </MainItem>
  </ItemGroup>
  <ItemGroup>
    <MainItem>
      <Key>Browne</Key>
      <Forenames>H. L.</Forenames>
      <PageNumber>4212</PageNumber>
    </MainItem>
  </ItemGroup>
  <ItemGroup>
    <MainItem>
      <Key>
        <KeyDitto>___ ___</KeyDitto>
      </Key>
      <Forenames>W. R. H .</Forenames>
      <PageNumber>3223</PageNumber>
    </MainItem>
  </ItemGroup>
  <ItemGroup>
    <MainItem>
      <Key>Buck</Key>
      <Forenames>F. A .</Forenames>
      <PageNumber>2569</PageNumber>
    </MainItem>
  </ItemGroup>
  <ItemGroup>
    <MainItem>
      <Key>Buckingham</Key>
      <Forenames>C. H.</Forenames>
      <PageNumber>2569</PageNumber>
    </MainItem>
  </ItemGroup>
  <ItemGroup>
    <MainItem>
      <Key>Buckland</Key>
      <Forenames>L. J. E.</Forenames>
      <PageNumber>3871</PageNumber>
    </MainItem>
  </ItemGroup>
  <ItemGroup>
    <MainItem>
      <Key>Bucknal</Key>
      <Forenames>R. D. H.</Forenames>
      <PageNumber>3068</PageNumber>
    </MainItem>
  </ItemGroup>
  <ItemGroup>
    <MainItem>
      <Key>Running</Key>
      <Forenames>W. H.</Forenames>
      <PageNumber>2569</PageNumber>
    </MainItem>
  </ItemGroup>
  <ItemGroup>
    <MainItem>
      <Key>Burdett</Key>
      <Forenames>E. W .</Forenames>
      <PageNumber>3222</PageNumber>
    </MainItem>
  </ItemGroup>
  <ItemGroup>
    <MainItem>
      <Key>Burdon</Key>
      <Forenames>R. M .</Forenames>
      <PageNumber>3223</PageNumber>
    </MainItem>
  </ItemGroup>
  <ItemGroup>
    <MainItem>
      <Key>Burke</Key>
      <Forenames>P. H</Forenames>
      <PageNumber>2509</PageNumber>
      <PageNumber>2894</PageNumber>
    </MainItem>
  </ItemGroup>
  <ItemGroup>
    <MainItem>
      <Key>Burn</Key>
      <Forenames>P .</Forenames>
      <PageNumber>3223</PageNumber>
    </MainItem>
  </ItemGroup>
  <ItemGroup>
    <MainItem>
      <Key>Bursey</Key>
      <Forenames>T. F.</Forenames>
      <Text>McL</Text>
      <PageNumber>2569</PageNumber>
    </MainItem>
  </ItemGroup>
  <ItemGroup>
    <MainItem>
      <Key>Bussell</Key>
      <Forenames>J. C .</Forenames>
      <PageNumber>3223</PageNumber>
    </MainItem>
  </ItemGroup>
  <ItemGroup>
    <MainItem>
      <Key>Butler</Key>
      <Forenames>A. H .</Forenames>
      <PageNumber>3387</PageNumber>
    </MainItem>
  </ItemGroup>
  <ItemGroup>
    <MainItem>
      <Key>Butterfield</Key>
      <Forenames>B. F. H.</Forenames>
      <PageNumber>3530</PageNumber>
    </MainItem>
  </ItemGroup>
  <ItemGroup>
    <MainItem>
      <Key>Byrne</Key>
      <Forenames>G. R .</Forenames>
      <PageNumber>4065</PageNumber>
    </MainItem>
  </ItemGroup>
  <ItemGroup>
    <MainItem>
      <Key>Caird</Key>
      <Forenames>D. R .</Forenames>
      <PageNumber>2731</PageNumber>
    </MainItem>
  </ItemGroup>
  <ItemGroup>
    <MainItem>
      <Key>Cant</Key>
      <Forenames>E. D .</Forenames>
      <PageNumber>2731</PageNumber>
    </MainItem>
  </ItemGroup>
  <ItemGroup>
    <MainItem>
      <Key>Carden</Key>
      <Forenames>F. G</Forenames>
      <PageNumber>2569</PageNumber>
      <PageNumber>3387</PageNumber>
    </MainItem>
  </ItemGroup>
  <ItemGroup>
    <MainItem>
      <Key>Oarey</Key>
      <Forenames>P. G .</Forenames>
      <PageNumber>3520</PageNumber>
    </MainItem>
  </ItemGroup>
  <ItemGroup>
    <MainItem>
      <Key>Carmichael</Key>
      <Forenames>W. B. G.</Forenames>
      <PageNumber>3530</PageNumber>
    </MainItem>
  </ItemGroup>
  <ItemGroup>
    <MainItem>
      <Key>Oarr</Key>
      <Forenames>W. R.</Forenames>
      <PageNumber>3068</PageNumber>
    </MainItem>
  </ItemGroup>
  <ItemGroup>
    <MainItem>
      <Key>Cassell</Key>
      <Forenames>A. D .</Forenames>
      <PageNumber>3387</PageNumber>
    </MainItem>
  </ItemGroup>
  <ItemGroup>
    <MainItem>
      <Key>Catterson-Smith</Key>
      <Forenames>S. J. G. A.</Forenames>
      <PageNumber>3678</PageNumber>
    </MainItem>
  </ItemGroup>
  <ItemGroup>
    <MainItem>
      <Key>Cavell</Key>
      <Forenames>R. G.</Forenames>
      <PageNumber>2569</PageNumber>
    </MainItem>
  </ItemGroup>
  <ItemGroup>
    <MainItem>
      <Key>Chamberlain</Key>
      <Forenames>L. L.</Forenames>
      <PageNumber>3068</PageNumber>
    </MainItem>
  </ItemGroup>
  <ItemGroup>
    <MainItem>
      <Key>Chamberlen</Key>
      <Forenames>E. F.</Forenames>
      <PageNumber>2569</PageNumber>
    </MainItem>
  </ItemGroup>
  <ItemGroup>
    <MainItem>
      <Key>Chamier</Key>
      <Forenames>A.</Forenames>
      <PageNumber>4212</PageNumber>
    </MainItem>
  </ItemGroup>
  <ItemGroup>
    <MainItem>
      <Key>Champion</Key>
      <Forenames>H. S.</Forenames>
      <PageNumber>2569</PageNumber>
    </MainItem>
  </ItemGroup>
  <ItemGroup>
    <MainItem>
      <Key>Channin</Key>
      <Forenames>P. R.</Forenames>
      <PageNumber>2569</PageNumber>
    </MainItem>
  </ItemGroup>
  <ItemGroup>
    <MainItem>
      <Key>Charlton</Key>
      <Forenames>F. J .</Forenames>
      <PageNumber>3872</PageNumber>
    </MainItem>
  </ItemGroup>
  <ItemGroup>
    <MainItem>
      <Key>Charnley</Key>
      <Forenames>F. H .</Forenames>
      <PageNumber>3679</PageNumber>
    </MainItem>
  </ItemGroup>
  <ItemGroup>
    <MainItem>
      <Key>Chetwynd-Palmer</Key>
      <Forenames>E. R.</Forenames>
      <PageNumber>2894</PageNumber>
    </MainItem>
  </ItemGroup>
  <ItemGroup>
    <MainItem>
      <Key>Churcher</Key>
      <Forenames>W. D .</Forenames>
      <PageNumber>3222</PageNumber>
    </MainItem>
  </ItemGroup>
  <ItemGroup>
    <MainItem>
      <Key>Clark</Key>
      <Forenames>C. D. Le G.</Forenames>
      <PageNumber>3068</PageNumber>
    </MainItem>
  </ItemGroup>
  <ItemGroup>
    <MainItem>
      <Key>Clarke</Key>
      <Forenames>B. G.</Forenames>
      <Text>. S</Text>
      <PageNumber>3872</PageNumber>
    </MainItem>
  </ItemGroup>
  <ItemGroup>
    <MainItem>
      <Key>
        <KeyDitto>___ ___ ___</KeyDitto>
      </Key>
      <Forenames>J. A .</Forenames>
      <PageNumber>3530</PageNumber>
    </MainItem>
  </ItemGroup>
  <ItemGroup>
    <MainItem>
      <Key>Clemo</Key>
      <Forenames>J.</Forenames>
      <PageNumber>3872</PageNumber>
    </MainItem>
  </ItemGroup>
  <ItemGroup>
    <MainItem>
      <Key>Clery</Key>
      <Forenames>C. B. L .</Forenames>
      <PageNumber>4213</PageNumber>
    </MainItem>
  </ItemGroup>
  <ItemGroup>
    <MainItem>
      <Key>Clews</Key>
      <Forenames>L. C .</Forenames>
      <PageNumber>2569</PageNumber>
    </MainItem>
  </ItemGroup>
  <ItemGroup>
    <MainItem>
      <Key>Climo</Key>
      <Text>SirS. H</Text>
      <PageNumber>4213</PageNumber>
    </MainItem>
  </ItemGroup>
  <ItemGroup>
    <MainItem>
      <Key>Cloran</Key>
      <Forenames>D. J. H .</Forenames>
      <PageNumber>2731</PageNumber>
    </MainItem>
  </ItemGroup>
  <ItemGroup>
    <MainItem>
      <Key>Coaker</Key>
      <Forenames>V. A.</Forenames>
      <PageNumber>3386</PageNumber>
    </MainItem>
  </ItemGroup>
  <ItemGroup>
    <MainItem>
      <Key>Cobb</Key>
      <Forenames>H. J. G .</Forenames>
      <PageNumber>3068</PageNumber>
    </MainItem>
  </ItemGroup>
  <ItemGroup>
    <MainItem>
      <Key>Collier</Key>
      <Forenames>W. J .</Forenames>
      <PageNumber>2569</PageNumber>
    </MainItem>
  </ItemGroup>
  <ItemGroup>
    <MainItem>
      <Key>Collins</Key>
      <Forenames>M. R .</Forenames>
      <PageNumber>2894</PageNumber>
    </MainItem>
  </ItemGroup>
  <ItemGroup>
    <MainItem>
      <Key>Collinson</Key>
      <Forenames>C. D. H.</Forenames>
      <PageNumber>2731</PageNumber>
    </MainItem>
  </ItemGroup>
  <ItemGroup>
    <MainItem>
      <Key>Collis</Key>
      <Forenames>F. S .</Forenames>
      <PageNumber>3387</PageNumber>
    </MainItem>
  </ItemGroup>
  <ItemGroup>
    <MainItem>
      <Key>Cokey</Key>
      <Text>JW. T</Text>
      <PageNumber>4212</PageNumber>
    </MainItem>
  </ItemGroup>
  <ItemGroup>
    <MainItem>
      <Key>Colwill</Key>
      <Forenames>R. F .</Forenames>
      <PageNumber>3871</PageNumber>
    </MainItem>
  </ItemGroup>
  <ItemGroup>
    <MainItem>
      <Key>Conder</Key>
      <Forenames>A. R.</Forenames>
      <PageNumber>3871</PageNumber>
    </MainItem>
  </ItemGroup>
  <ItemGroup>
    <MainItem>
      <Key>Cook</Key>
      <Forenames>T. P .</Forenames>
      <PageNumber>2731</PageNumber>
    </MainItem>
  </ItemGroup>
  <ItemGroup>
    <MainItem>
      <Key>
        <KeyDitto>___ ___ ___ ___</KeyDitto>
      </Key>
      <Forenames>W. G</Forenames>
      <PageNumber>3223</PageNumber>
      <PageNumber>3873</PageNumber>
    </MainItem>
  </ItemGroup>
  <ItemGroup>
    <MainItem>
      <Key>Cooper</Key>
      <Forenames>J. E.</Forenames>
      <PageNumber>3872</PageNumber>
    </MainItem>
  </ItemGroup>
  <ItemGroup>
    <MainItem>
      <Key>Copeland</Key>
      <Forenames>A. G. J.</Forenames>
      <PageNumber>3529</PageNumber>
    </MainItem>
  </ItemGroup>
  <ItemGroup>
    <MainItem>
      <Key>Corden</Key>
      <Forenames>C. I .</Forenames>
      <PageNumber>2569</PageNumber>
    </MainItem>
  </ItemGroup>
  <ItemGroup>
    <MainItem>
      <Key>Corfield</Key>
      <Forenames>V. C. W.</Forenames>
      <PageNumber>3530</PageNumber>
    </MainItem>
  </ItemGroup>
  <ItemGroup>
    <MainItem>
      <Key>Corley-Smith</Key>
      <Forenames>M. L.</Forenames>
      <PageNumber>3067</PageNumber>
      <PageNumber>3222</PageNumber>
    </MainItem>
  </ItemGroup>
  <ItemGroup>
    <MainItem>
      <Key>Cotterill</Key>
      <Forenames>F. H .</Forenames>
      <PageNumber>4212</PageNumber>
    </MainItem>
  </ItemGroup>
  <ItemGroup>
    <MainItem>
      <Key>Cotton</Key>
      <Forenames>J. T.</Forenames>
      <PageNumber>2731</PageNumber>
    </MainItem>
  </ItemGroup>
  <ItemGroup>
    <MainItem>
      <Key>Courtney</Key>
      <Forenames>J.</Forenames>
      <PageNumber>3678</PageNumber>
    </MainItem>
  </ItemGroup>
  <ItemGroup>
    <MainItem>
      <Key>Cox</Key>
      <Forenames>H. F .</Forenames>
      <PageNumber>3678</PageNumber>
    </MainItem>
  </ItemGroup>
  <ItemGroup>
    <MainItem>
      <Key>Cowling</Key>
      <Forenames>C. S. C.</Forenames>
      <PageNumber>4065</PageNumber>
    </MainItem>
  </ItemGroup>
  <ItemGroup>
    <MainItem>
      <Key>Craig</Key>
      <Forenames>C. C .</Forenames>
      <PageNumber>3530</PageNumber>
    </MainItem>
  </ItemGroup>
  <ItemGroup>
    <MainItem>
      <Key>Craigie</Key>
      <Forenames>P. N .</Forenames>
      <PageNumber>3678</PageNumber>
    </MainItem>
  </ItemGroup>
  <ItemGroup>
    <MainItem>
      <Key>Cramer</Key>
      <Forenames>J. M. C.</Forenames>
      <PageNumber>2569</PageNumber>
    </MainItem>
  </ItemGroup>
  <ItemGroup>
    <MainItem>
      <Key>Cranwill</Key>
      <Forenames>G. B .</Forenames>
      <PageNumber>2731</PageNumber>
    </MainItem>
  </ItemGroup>
  <ItemGroup>
    <MainItem>
      <Key>Crawley</Key>
      <Forenames>N. L.</Forenames>
      <PageNumber>3387</PageNumber>
    </MainItem>
  </ItemGroup>
  <ItemGroup>
    <MainItem>
      <Key>Creasy</Key>
      <Forenames>N. E .</Forenames>
      <PageNumber>3387</PageNumber>
    </MainItem>
  </ItemGroup>
  <ItemGroup>
    <MainItem>
      <Key>Crooke</Key>
      <Forenames>F. M. W.</Forenames>
      <PageNumber>2893</PageNumber>
    </MainItem>
  </ItemGroup>
  <ItemGroup>
    <MainItem>
      <Key>Cross</Key>
      <Forenames>S. G. N.</Forenames>
      <PageNumber>2569</PageNumber>
    </MainItem>
  </ItemGroup>
  <ItemGroup>
    <MainItem>
      <Key>Crossley</Key>
      <Forenames>J. F. F.</Forenames>
      <PageNumber>3530</PageNumber>
    </MainItem>
  </ItemGroup>
  <ItemGroup>
    <MainItem>
      <Key>Crum</Key>
      <Forenames>W. E.</Forenames>
      <PageNumber>2731</PageNumber>
    </MainItem>
  </ItemGroup>
  <ItemGroup>
    <MainItem>
      <Key>Cummins</Key>
      <Forenames>J. E.</Forenames>
      <PageNumber>3068</PageNumber>
    </MainItem>
  </ItemGroup>
  <ItemGroup>
    <MainItem>
      <Key>
        <KeyDitto>— ___ ___</KeyDitto>
      </Key>
      <Forenames>W .</Forenames>
      <PageNumber>2731</PageNumber>
    </MainItem>
  </ItemGroup>
  <ItemGroup>
    <MainItem>
      <Key>Cunningham</Key>
      <Forenames>W. E.</Forenames>
      <PageNumber>2731</PageNumber>
    </MainItem>
  </ItemGroup>
  <ItemGroup>
    <MainItem>
      <Key>Curie</Key>
      <Forenames>V .</Forenames>
      <PageNumber>2569</PageNumber>
    </MainItem>
  </ItemGroup>
  <ItemGroup>
    <MainItem>
      <Key>Dagge</Key>
      <Forenames>R. C.</Forenames>
      <PageNumber>3223</PageNumber>
    </MainItem>
  </ItemGroup>
  <ItemGroup>
    <MainItem>
      <Key>Daly</Key>
      <Forenames>F. O.</Forenames>
      <Text>AV. A</Text>
      <PageNumber>3223</PageNumber>
    </MainItem>
  </ItemGroup>
  <ItemGroup>
    <MainItem>
      <Key>Danby</Key>
      <Forenames>A. L.</Forenames>
      <PageNumber>4065</PageNumber>
    </MainItem>
  </ItemGroup>
  <ItemGroup>
    <MainItem>
      <Key>Dann</Key>
      <Forenames>C. F.</Forenames>
      <PageNumber>3678</PageNumber>
    </MainItem>
  </ItemGroup>
  <ItemGroup>
    <MainItem>
      <Key>Darwell</Key>
      <Forenames>G. P.</Forenames>
      <PageNumber>2569</PageNumber>
    </MainItem>
  </ItemGroup>
  <ItemGroup>
    <MainItem>
      <Key>Davenport</Key>
      <Forenames>R.</Forenames>
      <PageNumber>4065</PageNumber>
    </MainItem>
  </ItemGroup>
  <ItemGroup>
    <MainItem>
      <Key>Davidson</Key>
      <Forenames>G. N.</Forenames>
      <PageNumber>3871</PageNumber>
    </MainItem>
  </ItemGroup>
  <ItemGroup>
    <MainItem>
      <Key>Davies</Key>
      <Forenames>J. F.</Forenames>
      <PageNumber>3222</PageNumber>
    </MainItem>
  </ItemGroup>
  <ItemGroup>
    <MainItem>
      <Key>Davis</Key>
      <Forenames>H.</Forenames>
      <PageNumber>3678</PageNumber>
      <PageNumber>3678</PageNumber>
    </MainItem>
  </ItemGroup>
  <ItemGroup>
    <MainItem>
      <Key>De</Key>
      <Forenames>Brath</Forenames>
      <Text>, E. E</Text>
      <PageNumber>2569</PageNumber>
    </MainItem>
  </ItemGroup>
  <ItemGroup>
    <MainItem>
      <Key>Deacon</Key>
      <Forenames>A. E.</Forenames>
      <PageNumber>3222</PageNumber>
    </MainItem>
  </ItemGroup>
  <ItemGroup>
    <MainItem>
      <Key>Deans</Key>
      <Forenames>T. J.</Forenames>
      <PageNumber>3068</PageNumber>
    </MainItem>
  </ItemGroup>
  <ItemGroup>
    <MainItem>
      <Key>Dedman</Key>
      <Forenames>J. J.</Forenames>
      <Text>:</Text>
      <PageNumber>3387</PageNumber>
    </MainItem>
  </ItemGroup>
  <ItemGroup>
    <MainItem>
      <Key>Deighton</Key>
      <Forenames>F. J.</Forenames>
      <PageNumber>4064</PageNumber>
    </MainItem>
  </ItemGroup>
  <ItemGroup>
    <MainItem>
      <Key>Delamain</Key>
      <Text>J. H</Text>
      <PageNumber>3223</PageNumber>
    </MainItem>
  </ItemGroup>
  <ItemGroup>
    <MainItem>
      <Key>
        <KeyDitto>___ ___ ___</KeyDitto>
      </Key>
      <Title>Sir</Title>
      <Forenames>W. S.</Forenames>
      <PageNumber>4065</PageNumber>
    </MainItem>
  </ItemGroup>
  <ItemGroup>
    <MainItem>
      <Key>Dening</Key>
      <Forenames>R.</Forenames>
      <PageNumber>2730</PageNumber>
    </MainItem>
  </ItemGroup>
  <ItemGroup>
    <MainItem>
      <Key>Denny</Key>
      <Forenames>M. P. R.</Forenames>
      <PageNumber>2569</PageNumber>
    </MainItem>
  </ItemGroup>
  <ItemGroup>
    <MainItem>
      <Key>Dickens</Key>
      <Forenames>A. C.</Forenames>
      <PageNumber>3387</PageNumber>
    </MainItem>
  </ItemGroup>
  <ItemGroup>
    <MainItem>
      <Key>
        <KeyDitto>___ ___</KeyDitto>
      </Key>
      <Forenames>H. E.</Forenames>
      <PageNumber>3068</PageNumber>
    </MainItem>
  </ItemGroup>
  <ItemGroup>
    <MainItem>
      <Key>Dickson</Key>
      <Forenames>E. J.</Forenames>
      <PageNumber>3872</PageNumber>
    </MainItem>
  </ItemGroup>
  <ItemGroup>
    <MainItem>
      <Key>Digby</Key>
      <Text>PR. .:</Text>
      <PageNumber>3872</PageNumber>
    </MainItem>
  </ItemGroup>
  <ItemGroup>
    <MainItem>
      <Key>Donavan</Key>
      <Forenames>C. H.</Forenames>
      <PageNumber>2731</PageNumber>
    </MainItem>
  </ItemGroup>
  <ItemGroup>
    <MainItem>
      <Key>Donovan</Key>
      <Forenames>D. B. E .</Forenames>
      <PageNumber>3223</PageNumber>
    </MainItem>
  </ItemGroup>
  <ItemGroup>
    <MainItem>
      <Key>Doudriey</Key>
      <Forenames>G. W.</Forenames>
      <PageNumber>2569</PageNumber>
    </MainItem>
  </ItemGroup>
  <ItemGroup>
    <MainItem>
      <Key>Drack</Key>
      <Forenames>W. J.</Forenames>
      <PageNumber>2569</PageNumber>
    </MainItem>
  </ItemGroup>
  <ItemGroup>
    <MainItem>
      <Key>Dron</Key>
      <Forenames>C. W.</Forenames>
      <PageNumber>2569</PageNumber>
    </MainItem>
  </ItemGroup>
  <ItemGroup>
    <MainItem>
      <Key>Drought</Key>
      <Forenames>T. D. B .</Forenames>
      <PageNumber>3387</PageNumber>
    </MainItem>
  </ItemGroup>
  <ItemGroup>
    <MainItem>
      <Key>Dunkerton</Key>
      <Forenames>E. L. H.</Forenames>
      <PageNumber>4212</PageNumber>
    </MainItem>
  </ItemGroup>
  <ItemGroup>
    <MainItem>
      <Key>Dunley-Owen</Key>
      <Forenames>A. H. U .</Forenames>
      <PageNumber>3068</PageNumber>
    </MainItem>
  </ItemGroup>
  <ItemGroup>
    <MainItem>
      <Key>Dunlop</Key>
      <Forenames>H. J.</Forenames>
      <PageNumber>3222</PageNumber>
    </MainItem>
  </ItemGroup>
  <ItemGroup>
    <MainItem>
      <Key>Dunn</Key>
      <Forenames>D.</Forenames>
      <PageNumber>4065</PageNumber>
    </MainItem>
  </ItemGroup>
  <ItemGroup>
    <MainItem>
      <Key>Durston</Key>
      <Forenames>R. E.</Forenames>
      <PageNumber>3678</PageNumber>
    </MainItem>
  </ItemGroup>
  <ItemGroup>
    <MainItem>
      <Key>Dutton</Key>
      <Forenames>E. F. H.</Forenames>
      <PageNumber>3068</PageNumber>
    </MainItem>
  </ItemGroup>
  <ItemGroup>
    <MainItem>
      <Key>Echlin</Key>
      <Forenames>F. C.</Forenames>
      <PageNumber>3529</PageNumber>
    </MainItem>
  </ItemGroup>
  <ItemGroup>
    <MainItem>
      <Key>Edge</Key>
      <Forenames>E. H.</Forenames>
      <PageNumber>3679</PageNumber>
    </MainItem>
  </ItemGroup>
  <ItemGroup>
    <MainItem>
      <Key>
        <KeyDitto>___ ___ ___ ___</KeyDitto>
      </Key>
      <Forenames>F. L.</Forenames>
      <PageNumber>2569</PageNumber>
    </MainItem>
  </ItemGroup>
  <ItemGroup>
    <MainItem>
      <Key>Edwards</Key>
      <Forenames>F. H.</Forenames>
      <PageNumber>4212</PageNumber>
    </MainItem>
  </ItemGroup>
  <ItemGroup>
    <MainItem>
      <Key>
        <KeyDitto>___ ___ ___</KeyDitto>
      </Key>
      <Forenames>M. F.</Forenames>
      <PageNumber>3223</PageNumber>
    </MainItem>
  </ItemGroup>
  <ItemGroup>
    <MainItem>
      <Key>Elgood</Key>
      <Forenames>H. R.</Forenames>
      <PageNumber>2569</PageNumber>
    </MainItem>
  </ItemGroup>
  <ItemGroup>
    <MainItem>
      <Key>Elliott</Key>
      <Forenames>A. C.</Forenames>
      <PageNumber>4065</PageNumber>
    </MainItem>
  </ItemGroup>
  <ItemGroup>
    <MainItem>
      <Key>
        <KeyDitto>___ ___</KeyDitto>
      </Key>
      <Forenames>E. T.</Forenames>
      <PageNumber>4065</PageNumber>
    </MainItem>
  </ItemGroup>
  <ItemGroup>
    <MainItem>
      <Key>Elsmie</Key>
      <Forenames>A. M. S.</Forenames>
      <PageNumber>4065</PageNumber>
    </MainItem>
  </ItemGroup>
  <ItemGroup>
    <MainItem>
      <Key>Elton-Williams-</Key>
      <Forenames>J</Forenames>
      <Text>ervis, dE</Text>
      <PageNumber>4065</PageNumber>
    </MainItem>
  </ItemGroup>
  <ItemGroup>
    <MainItem>
      <Key>English</Key>
      <Forenames>F.W.H.</Forenames>
      <PageNumber>3068</PageNumber>
    </MainItem>
  </ItemGroup>
  <ItemGroup>
    <MainItem>
      <Key>Erskine</Key>
      <Forenames>W. R.</Forenames>
      <PageNumber>2731</PageNumber>
    </MainItem>
  </ItemGroup>
  <ItemGroup>
    <MainItem>
      <Key>Eustace</Key>
      <Forenames>E. A. R.</Forenames>
      <Text>.:,</Text>
      <PageNumber>3223</PageNumber>
    </MainItem>
  </ItemGroup>
  <ItemGroup>
    <MainItem>
      <Key>Evans</Key>
      <Forenames>C. F.</Forenames>
      <PageNumber>2731</PageNumber>
    </MainItem>
  </ItemGroup>
  <ItemGroup>
    <MainItem>
      <Key>
        <KeyDitto>___ ___ ___</KeyDitto>
      </Key>
      <Forenames>F. L.</Forenames>
      <PageNumber>3872</PageNumber>
    </MainItem>
  </ItemGroup>
  <ItemGroup>
    <MainItem>
      <Key>Everett</Key>
      <Forenames>W. H.</Forenames>
      <PageNumber>4065</PageNumber>
    </MainItem>
  </ItemGroup>
  <ItemGroup>
    <MainItem>
      <Key>Ewers</Key>
      <Forenames>L. F.</Forenames>
      <PageNumber>2569</PageNumber>
    </MainItem>
  </ItemGroup>
  <ItemGroup>
    <MainItem>
      <Key>Farr</Key>
      <Forenames>C. J.</Forenames>
      <PageNumber>2568</PageNumber>
    </MainItem>
  </ItemGroup>
  <ItemGroup>
    <MainItem>
      <Key>Featherstone</Key>
      <Forenames>B.</Forenames>
      <Text>*K</Text>
      <PageNumber>4212</PageNumber>
    </MainItem>
  </ItemGroup>
  <ItemGroup>
    <MainItem>
      <Key>Fennell</Key>
      <Forenames>W. G.</Forenames>
      <PageNumber>3068</PageNumber>
    </MainItem>
  </ItemGroup>
  <ItemGroup>
    <MainItem>
      <Key>Figgins</Key>
      <Forenames>A. P.</Forenames>
      <PageNumber>2569</PageNumber>
    </MainItem>
  </ItemGroup>
  <ItemGroup>
    <MainItem>
      <Key>Fitzgerald</Key>
      <Forenames>D. C. V.</Forenames>
      <PageNumber>2731</PageNumber>
    </MainItem>
  </ItemGroup>
  <ItemGroup>
    <MainItem>
      <Key>Fitz-Maui</Key>
      <Text>ice, W. H. »</Text>
      <PageNumber>3678</PageNumber>
    </MainItem>
  </ItemGroup>
  <ItemGroup>
    <MainItem>
      <Key>Fitzpatrick</Key>
      <Forenames>M. J. J.</Forenames>
      <PageNumber>2569</PageNumber>
    </MainItem>
  </ItemGroup>
  <ItemGroup>
    <MainItem>
      <Key>Flannery</Key>
      <Forenames>J.</Forenames>
      <PageNumber>4065</PageNumber>
    </MainItem>
  </ItemGroup>
  <ItemGroup>
    <MainItem>
      <Key>Folkard</Key>
      <Forenames>W. F. D.</Forenames>
      <PageNumber>3223</PageNumber>
    </MainItem>
  </ItemGroup>
  <ItemGroup>
    <MainItem>
      <Key>Forbes-Taylor</Key>
      <Forenames>E. M.</Forenames>
      <PageNumber>3222</PageNumber>
    </MainItem>
  </ItemGroup>
  <ItemGroup>
    <MainItem>
      <Key>Forrester</Key>
      <Forenames>H. E.</Forenames>
      <PageNumber>2569</PageNumber>
    </MainItem>
  </ItemGroup>
  <ItemGroup>
    <MainItem>
      <Key>Forshaw</Key>
      <Forenames>W. T.</Forenames>
      <PageNumber>3068</PageNumber>
    </MainItem>
  </ItemGroup>
  <ItemGroup>
    <MainItem>
      <Key>Fortune</Key>
      <Forenames>G. R.</Forenames>
      <PageNumber>2731</PageNumber>
    </MainItem>
  </ItemGroup>
  <ItemGroup>
    <MainItem>
      <Key>Foster</Key>
      <Forenames>M. R.</Forenames>
      <PageNumber>3078</PageNumber>
    </MainItem>
  </ItemGroup>
  <ItemGroup>
    <MainItem>
      <Key>Fox</Key>
      <Forenames>J .</Forenames>
      <PageNumber>3678</PageNumber>
    </MainItem>
  </ItemGroup>
  <ItemGroup>
    <MainItem>
      <Key>Francis</Key>
      <Forenames>M.</Forenames>
      <Text>FT</Text>
      <PageNumber>2894</PageNumber>
    </MainItem>
  </ItemGroup>
  <ItemGroup>
    <MainItem>
      <Key>Frankish</Key>
      <Forenames>W. M.</Forenames>
      <PageNumber>2731</PageNumber>
    </MainItem>
  </ItemGroup>
  <ItemGroup>
    <MainItem>
      <Key>Frizzell</Key>
      <Forenames>W. G.</Forenames>
      <PageNumber>2569</PageNumber>
    </MainItem>
  </ItemGroup>
  <ItemGroup>
    <MainItem>
      <Key>Fuge</Key>
      <Forenames>T. L. M.</Forenames>
      <Text>... \</Text>
      <PageNumber>4212</PageNumber>
    </MainItem>
  </ItemGroup>
  <ItemGroup>
    <MainItem>
      <Key>Fullerton</Key>
      <Forenames>G. A.</Forenames>
      <PageNumber>4212</PageNumber>
    </MainItem>
  </ItemGroup>
  <ItemGroup>
    <MainItem>
      <Key>Fulton</Key>
      <Forenames>C. F. V.</Forenames>
      <PageNumber>3387</PageNumber>
    </MainItem>
  </ItemGroup>
  <ItemGroup>
    <MainItem>
      <Key>Garvie</Key>
      <Forenames>K. C.</Forenames>
      <PageNumber>3223</PageNumber>
      <PageNumber>3530</PageNumber>
    </MainItem>
  </ItemGroup>
  <ItemGroup>
    <MainItem>
      <Key>Gasson</Key>
      <Forenames>H. T.</Forenames>
      <PageNumber>3872</PageNumber>
    </MainItem>
  </ItemGroup>
  <ItemGroup>
    <MainItem>
      <Key>Gault</Key>
      <Forenames>C .</Forenames>
      <PageNumber>3068</PageNumber>
    </MainItem>
  </ItemGroup>
  <KeyDitto>___ ___ ___ ___ ...</KeyDitto>
  <ItemGroup>
    <MainItem>
      <Key>Gazzard</Key>
      <Forenames>T.</Forenames>
      <PageNumber>2731</PageNumber>
    </MainItem>
  </ItemGroup>
  <ItemGroup>
    <MainItem>
      <Key>Gearv</Key>
      <Forenames>H. V.</Forenames>
      <PageNumber>3223</PageNumber>
      <PageNumber>3530</PageNumber>
    </MainItem>
  </ItemGroup>
  <ItemGroup>
    <MainItem>
      <Key>Geddie</Key>
      <Forenames>D. W.</Forenames>
      <PageNumber>2731</PageNumber>
    </MainItem>
  </ItemGroup>
  <ItemGroup>
    <MainItem>
      <Key>Gee</Key>
      <Forenames>W. H. S.</Forenames>
      <PageNumber>2569</PageNumber>
    </MainItem>
  </ItemGroup>
  <ItemGroup>
    <MainItem>
      <Key>George</Key>
      <Forenames>S. P.</Forenames>
      <PageNumber>3387</PageNumber>
    </MainItem>
  </ItemGroup>
  <ItemGroup>
    <MainItem>
      <Key>Gerard</Key>
      <Forenames>E. L.</Forenames>
      <PageNumber>4065</PageNumber>
    </MainItem>
  </ItemGroup>
  <ItemGroup>
    <MainItem>
      <Key>Gething</Key>
      <Forenames>L. R</Forenames>
      <PageNumber>2569</PageNumber>
    </MainItem>
  </ItemGroup>
  <ItemGroup>
    <MainItem>
      <Key>Gibson</Key>
      <Forenames>F. J. Richardson</Forenames>
      <Text>, see Richardson-Gibson, F. J. Gilbert, C</Text>
      <PageNumber>3529</PageNumber>
    </MainItem>
  </ItemGroup>
  <ItemGroup>
    <MainItem>
      <Key>
        <KeyDitto>___ ___ ___</KeyDitto>
      </Key>
      <Forenames>E. C.</Forenames>
      <PageNumber>3223</PageNumber>
    </MainItem>
  </ItemGroup>
  <ItemGroup>
    <MainItem>
      <Key>Girling</Key>
      <Forenames>J. B.</Forenames>
      <PageNumber>4213</PageNumber>
    </MainItem>
  </ItemGroup>
  <ItemGroup>
    <MainItem>
      <Key>Godfray</Key>
      <Forenames>T. D.</Forenames>
      <PageNumber>3223</PageNumber>
    </MainItem>
  </ItemGroup>
  <ItemGroup>
    <MainItem>
      <Key>Godly</Key>
      <Forenames>B. W. T.</Forenames>
      <PageNumber>2569</PageNumber>
    </MainItem>
  </ItemGroup>
  <ItemGroup>
    <MainItem>
      <Key>Goldfrap</Key>
      <Forenames>H. W.</Forenames>
      <PageNumber>2731</PageNumber>
      <PageNumber>2731</PageNumber>
    </MainItem>
  </ItemGroup>
  <ItemGroup>
    <MainItem>
      <Key>Goode</Key>
      <Forenames>R. L</Forenames>
      <PageNumber>3529</PageNumber>
    </MainItem>
  </ItemGroup>
  <ItemGroup>
    <MainItem>
      <Key>Gopalkrishna</Key>
      <Forenames>Ramrao Padbidri</Forenames>
      <PageNumber>3222</PageNumber>
    </MainItem>
  </ItemGroup>
  <ItemGroup>
    <MainItem>
      <Key>Gordon</Key>
      <Forenames>R. D. L</Forenames>
      <PageNumber>3223</PageNumber>
    </MainItem>
  </ItemGroup>
  <ItemGroup>
    <MainItem>
      <Key>Gorringe</Key>
      <Forenames>W. P. Hugh</Forenames>
      <Text>, see Hugh-Gorringe, W. P. Gott, G. A</Text>
      <PageNumber>3872</PageNumber>
    </MainItem>
  </ItemGroup>
  <ItemGroup>
    <MainItem>
      <Key>Gough</Key>
      <Forenames>H. A. K.</Forenames>
      <PageNumber>3067</PageNumber>
    </MainItem>
  </ItemGroup>
  <ItemGroup>
    <MainItem>
      <Key>Gowland</Key>
      <Forenames>C. J.</Forenames>
      <PageNumber>2731</PageNumber>
    </MainItem>
  </ItemGroup>
  <ItemGroup>
    <MainItem>
      <Key>Grace</Key>
      <Forenames>H. G.</Forenames>
      <PageNumber>3871</PageNumber>
    </MainItem>
  </ItemGroup>
  <ItemGroup>
    <MainItem>
      <Key>Graham</Key>
      <Forenames>G. D.</Forenames>
      <PageNumber>3387</PageNumber>
    </MainItem>
  </ItemGroup>
  <ItemGroup>
    <MainItem>
      <Key>
        <KeyDitto>___ ___</KeyDitto>
      </Key>
      <Forenames>J. P.</Forenames>
      <PageNumber>4212</PageNumber>
    </MainItem>
  </ItemGroup>
  <ItemGroup>
    <MainItem>
      <Key>Grant</Key>
      <Forenames>A. J.</Forenames>
      <PageNumber>2568</PageNumber>
    </MainItem>
  </ItemGroup>
  <ItemGroup>
    <MainItem>
      <Key>
        <KeyDitto>— ___ ___</KeyDitto>
      </Key>
      <Forenames>D. S.</Forenames>
      <PageNumber>4213</PageNumber>
    </MainItem>
  </ItemGroup>
  <ItemGroup>
    <MainItem>
      <Key>Gray</Key>
      <Forenames>E. St</Forenames>
      <Text>. C</Text>
      <PageNumber>3223</PageNumber>
    </MainItem>
  </ItemGroup>
  <ItemGroup>
    <MainItem>
      <Key>Greenhouse</Key>
      <Forenames>F. S.</Forenames>
      <PageNumber>4212</PageNumber>
    </MainItem>
  </ItemGroup>
  <ItemGroup>
    <MainItem>
      <Key>
        <KeyDitto>___ ___</KeyDitto>
      </Key>
      <Forenames>H. W.</Forenames>
      <PageNumber>3386</PageNumber>
    </MainItem>
  </ItemGroup>
  <ItemGroup>
    <MainItem>
      <Key>
        <KeyDitto>___ ___ ___</KeyDitto>
      </Key>
      <Forenames>P. A.</Forenames>
      <PageNumber>3222</PageNumber>
    </MainItem>
  </ItemGroup>
  <ItemGroup>
    <MainItem>
      <Key>
        <KeyDitto>___ ___ ___</KeyDitto>
      </Key>
      <Forenames>W. G.</Forenames>
      <PageNumber>4065</PageNumber>
    </MainItem>
  </ItemGroup>
  <ItemGroup>
    <MainItem>
      <Key>Greer</Key>
      <Forenames>E. R.</Forenames>
      <PageNumber>3222</PageNumber>
    </MainItem>
  </ItemGroup>
  <ItemGroup>
    <MainItem>
      <Key>
        <KeyDitto>___ ___ ___</KeyDitto>
      </Key>
      <Text>t. Met}</Text>
      <PageNumber>4065</PageNumber>
    </MainItem>
  </ItemGroup>
  <ItemGroup>
    <MainItem>
      <Key>Griffiths</Key>
      <Forenames>R. W.</Forenames>
      <PageNumber>2731</PageNumber>
    </MainItem>
  </ItemGroup>
  <ItemGroup>
    <MainItem>
      <Key>Gripper</Key>
      <Forenames>H. B.</Forenames>
      <PageNumber>3873</PageNumber>
    </MainItem>
  </ItemGroup>
  <ItemGroup>
    <MainItem>
      <Key>Guise</Key>
      <Forenames>C. P.</Forenames>
      <PageNumber>4065</PageNumber>
    </MainItem>
  </ItemGroup>
  <ItemGroup>
    <MainItem>
      <Key>Gul</Key>
      <Forenames>Sher Khan</Forenames>
      <PageNumber>2568</PageNumber>
    </MainItem>
  </ItemGroup>
  <ItemGroup>
    <MainItem>
      <Key>Gulliland</Key>
      <Forenames>C. C.</Forenames>
      <PageNumber>3387</PageNumber>
    </MainItem>
  </ItemGroup>
  <ItemGroup>
    <MainItem>
      <Key>Hall</Key>
      <Forenames>T. C.</Forenames>
      <PageNumber>3223</PageNumber>
    </MainItem>
  </ItemGroup>
  <ItemGroup>
    <MainItem>
      <Key>Harboard</Key>
      <Forenames>C. R.</Forenames>
      <PageNumber>3614</PageNumber>
    </MainItem>
  </ItemGroup>
  <ItemGroup>
    <MainItem>
      <Key>Harcourt</Key>
      <Forenames>C. R.</Forenames>
      <PageNumber>4212</PageNumber>
    </MainItem>
  </ItemGroup>
  <ItemGroup>
    <MainItem>
      <Key>Harding</Key>
      <Forenames>A. W.</Forenames>
      <PageNumber>3871</PageNumber>
    </MainItem>
  </ItemGroup>
  <ItemGroup>
    <MainItem>
      <Key>Hare</Key>
      <Forenames>I. L. O</Forenames>
      <Text>'H</Text>
      <PageNumber>3678</PageNumber>
    </MainItem>
  </ItemGroup>
  <ItemGroup>
    <MainItem>
      <Key>Harris</Key>
      <Forenames>N. A.</Forenames>
      <PageNumber>3386</PageNumber>
    </MainItem>
  </ItemGroup>
  <ItemGroup>
    <MainItem>
      <Key>Harrison</Key>
      <Forenames>J. W. H.</Forenames>
      <Text>,</Text>
      <PageNumber>3222</PageNumber>
    </MainItem>
  </ItemGroup>
  <ItemGroup>
    <MainItem>
      <Key>
        <KeyDitto>___ ___</KeyDitto>
      </Key>
      <Forenames>K. H</Forenames>
      <PageNumber>3678</PageNumber>
      <PageNumber>2894</PageNumber>
    </MainItem>
  </ItemGroup>
  <ItemGroup>
    <MainItem>
      <Key>
        <KeyDitto>___ ___ ___ ___ ___</KeyDitto>
      </Key>
      <Forenames>W. B.</Forenames>
      <PageNumber>3223</PageNumber>
    </MainItem>
  </ItemGroup>
  <ItemGroup>
    <MainItem>
      <Key>Hart</Key>
      <Forenames>N. B</Forenames>
      <Text>,</Text>
      <PageNumber>2569</PageNumber>
    </MainItem>
  </ItemGroup>
  <ItemGroup>
    <MainItem>
      <Key>Hartmann</Key>
      <Forenames>W. H.</Forenames>
      <PageNumber>2893</PageNumber>
    </MainItem>
  </ItemGroup>
  <ItemGroup>
    <MainItem>
      <Key>Harvey</Key>
      <Forenames>A.</Forenames>
      <PageNumber>2731</PageNumber>
    </MainItem>
  </ItemGroup>
  <ItemGroup>
    <MainItem>
      <Key>
        <KeyDitto>___ ___</KeyDitto>
      </Key>
      <Forenames>C</Forenames>
      <PageNumber>2731</PageNumber>
    </MainItem>
  </ItemGroup>
  <ItemGroup>
    <MainItem>
      <Key>Hawkes</Key>
      <Forenames>T. Y.</Forenames>
      <PageNumber>2569</PageNumber>
    </MainItem>
  </ItemGroup>
  <ItemGroup>
    <MainItem>
      <Key>Hawkins</Key>
      <Forenames>F. T.</Forenames>
      <PageNumber>4065</PageNumber>
    </MainItem>
  </ItemGroup>
  <ItemGroup>
    <MainItem>
      <Key>Hay</Key>
      <Forenames>W. N.</Forenames>
      <PageNumber>4278</PageNumber>
    </MainItem>
  </ItemGroup>
  <ItemGroup>
    <MainItem>
      <Key>Heard</Key>
      <Forenames>R.</Forenames>
      <PageNumber>2893</PageNumber>
    </MainItem>
  </ItemGroup>
  <ItemGroup>
    <MainItem>
      <Key>Hearn</Key>
      <Forenames>L. A</Forenames>
      <PageNumber>2893</PageNumber>
      <PageNumber>2569</PageNumber>
    </MainItem>
  </ItemGroup>
  <ItemGroup>
    <MainItem>
      <Key>
        <KeyDitto>___ ___</KeyDitto>
      </Key>
      <Forenames>W. S. H.</Forenames>
      <PageNumber>4212</PageNumber>
    </MainItem>
  </ItemGroup>
  <ItemGroup>
    <MainItem>
      <Key>Henderson</Key>
      <Forenames>E. G. S.</Forenames>
      <PageNumber>3223</PageNumber>
    </MainItem>
  </ItemGroup>
  <ItemGroup>
    <MainItem>
      <Key>Henfrey</Key>
      <Forenames>T. H.</Forenames>
      <PageNumber>2569</PageNumber>
    </MainItem>
  </ItemGroup>
  <ItemGroup>
    <MainItem>
      <Key>Henshaw</Key>
      <Forenames>A. G.</Forenames>
      <PageNumber>3678</PageNumber>
    </MainItem>
  </ItemGroup>
  <ItemGroup>
    <MainItem>
      <Key>Herbert</Key>
      <Forenames>A. E.</Forenames>
      <PageNumber>3613</PageNumber>
    </MainItem>
  </ItemGroup>
  <ItemGroup>
    <MainItem>
      <Key>Herdon</Key>
      <Forenames>H. E.</Forenames>
      <PageNumber>2569</PageNumber>
    </MainItem>
  </ItemGroup>
  <ItemGroup>
    <MainItem>
      <Key>Herman</Key>
      <Forenames>C. R.</Forenames>
      <PageNumber>3872</PageNumber>
    </MainItem>
  </ItemGroup>
  <ItemGroup>
    <MainItem>
      <Key>Hesketh</Key>
      <Forenames>W.</Forenames>
      <PageNumber>3222</PageNumber>
    </MainItem>
  </ItemGroup>
  <ItemGroup>
    <MainItem>
      <Key>Heywood</Key>
      <Forenames>H. C. L</Forenames>
      <PageNumber>2894</PageNumber>
    </MainItem>
  </ItemGroup>
  <ItemGroup>
    <MainItem>
      <Key>Higgens</Key>
      <Forenames>C. R.</Forenames>
      <PageNumber>3529</PageNumber>
    </MainItem>
  </ItemGroup>
  <ItemGroup>
    <MainItem>
      <Key>Higgs</Key>
      <Forenames>R. N.</Forenames>
      <PageNumber>3873</PageNumber>
    </MainItem>
  </ItemGroup>
  <ItemGroup>
    <MainItem>
      <Key>Hill</Key>
      <Forenames>B. B.</Forenames>
      <PageNumber>2893</PageNumber>
    </MainItem>
  </ItemGroup>
  <KeyDitto>___</KeyDitto>
  <ItemGroup>
    <MainItem>
      <Key>
        <KeyDitto>___ ___ ___</KeyDitto>
      </Key>
      <Forenames>L. E. Raven</Forenames>
      <Text>, see RavenHill, L. E Hodgson, G. B</Text>
      <PageNumber>3872</PageNumber>
    </MainItem>
  </ItemGroup>
  <ItemGroup>
    <MainItem>
      <Key>Hogan</Key>
      <Forenames>P. T.</Forenames>
      <PageNumber>3677</PageNumber>
    </MainItem>
  </ItemGroup>
  <ItemGroup>
    <MainItem>
      <Key>Holdcroft</Key>
      <Forenames>G. E.</Forenames>
      <PageNumber>2731</PageNumber>
    </MainItem>
  </ItemGroup>
  <ItemGroup>
    <MainItem>
      <Key>Holland-Pryor</Key>
      <Forenames>P.</Forenames>
      <PageNumber>3222</PageNumber>
    </MainItem>
  </ItemGroup>
  <ItemGroup>
    <MainItem>
      <Key>Holt</Key>
      <Forenames>C. H.</Forenames>
      <PageNumber>3530</PageNumber>
    </MainItem>
  </ItemGroup>
  <ItemGroup>
    <MainItem>
      <Key>Holwilr</Key>
      <Forenames>R. F.</Forenames>
      <PageNumber>3872</PageNumber>
    </MainItem>
  </ItemGroup>
  <ItemGroup>
    <MainItem>
      <Key>Horner</Key>
      <Forenames>F. H. F.</Forenames>
      <PageNumber>3678</PageNumber>
    </MainItem>
  </ItemGroup>
  <ItemGroup>
    <MainItem>
      <Key>Hotham</Key>
      <Forenames>G. I. M.</Forenames>
      <PageNumber>2894</PageNumber>
    </MainItem>
  </ItemGroup>
  <ItemGroup>
    <MainItem>
      <Key>Howard</Key>
      <Forenames>M. C.</Forenames>
      <PageNumber>2569</PageNumber>
    </MainItem>
  </ItemGroup>
  <ItemGroup>
    <MainItem>
      <Key>Howell</Key>
      <Forenames>R. W.</Forenames>
      <PageNumber>2894</PageNumber>
    </MainItem>
  </ItemGroup>
  <ItemGroup>
    <MainItem>
      <Key>Howes</Key>
      <Forenames>H. C.</Forenames>
      <PageNumber>3873</PageNumber>
    </MainItem>
  </ItemGroup>
  <ItemGroup>
    <MainItem>
      <Key>Howland</Key>
      <Forenames>C. C.</Forenames>
      <PageNumber>3068</PageNumber>
    </MainItem>
  </ItemGroup>
  <ItemGroup>
    <MainItem>
      <Key>Huddleston</Key>
      <Forenames>J. H</Forenames>
      <PageNumber>2894</PageNumber>
    </MainItem>
  </ItemGroup>
  <ItemGroup>
    <MainItem>
      <Key>Hugh-Gorringe</Key>
      <Forenames>W</Forenames>
      <Text>,</Text>
      <PageNumber>3222</PageNumber>
    </MainItem>
  </ItemGroup>
  <ItemGroup>
    <MainItem>
      <Key>Hughes</Key>
      <Forenames>A. H.</Forenames>
      <PageNumber>3873</PageNumber>
    </MainItem>
  </ItemGroup>
  <ItemGroup>
    <MainItem>
      <Key>
        <KeyDitto>___ ___</KeyDitto>
      </Key>
      <Forenames>H</Forenames>
      <PageNumber>3222</PageNumber>
      <PageNumber>3530</PageNumber>
    </MainItem>
  </ItemGroup>
  <ItemGroup>
    <MainItem>
      <Key>Humfrey</Key>
      <Forenames>B.</Forenames>
      <PageNumber>2568</PageNumber>
    </MainItem>
  </ItemGroup>
  <ItemGroup>
    <MainItem>
      <Key>Humm</Key>
      <Forenames>P. S.</Forenames>
      <PageNumber>4212</PageNumber>
    </MainItem>
  </ItemGroup>
  <ItemGroup>
    <MainItem>
      <Key>Hunt</Key>
      <Forenames>E. C.</Forenames>
      <Text>..:</Text>
      <PageNumber>3872</PageNumber>
      <PageNumber>2569</PageNumber>
    </MainItem>
  </ItemGroup>
  <ItemGroup>
    <MainItem>
      <Key>Huntley</Key>
      <Forenames>W. B.</Forenames>
      <PageNumber>3530</PageNumber>
    </MainItem>
  </ItemGroup>
  <ItemGroup>
    <MainItem>
      <Key>
        <KeyDitto>___ ___ ___ ___</KeyDitto>
      </Key>
      <Forenames>G. S .</Forenames>
      <PageNumber>3386</PageNumber>
    </MainItem>
  </ItemGroup>
  <ItemGroup>
    <MainItem>
      <Key>
        <KeyDitto>___ ___</KeyDitto>
      </Key>
      <Forenames>R. H.</Forenames>
      <PageNumber>2569</PageNumber>
    </MainItem>
  </ItemGroup>
  <KeyDitto>___ ___</KeyDitto>
</Index>

