<?xml version="1.0" encoding="UTF-8"?>
<Index xmlns="http://www.tso.co.uk/assets/namespace/gazetteindex" editionCode="L" page="255" pageID="https://www.thegazette.co.uk/id/London/index/year/1920/volume/2/page/255" pagePDF="https://www.thegazette.co.uk/London/index/year/1920/volume/2/page/255" pageRDF="https://www.thegazette.co.uk/London/index/year/1920/volume/2/page/255?view=linked-data" type="index" volume="2" year="1920">
  <ItemGroup>
    <MainItem>
      <Key>Brewer</Key>
      <Title>2nd Lt.</Title>
      <Forenames>L.</Forenames>
      <Text>(Lt.)</Text>
      <PageNumber>4680</PageNumber>
    </MainItem>
  </ItemGroup>
  <ItemGroup>
    <MainItem>
      <Key>Brewill</Key>
      <Title>Capt.</Title>
      <Forenames>L. C.</Forenames>
      <Text>{temp. Adjt.)</Text>
      <PageNumber>4826</PageNumber>
    </MainItem>
  </ItemGroup>
  <ItemGroup>
    <MainItem>
      <Key>Bridge</Key>
      <Title>Lt.</Title>
      <Forenames>C. B.</Forenames>
      <Text>
        <Honour>G.C.</Honour>
      </Text>
      <PageNumber>6985</PageNumber>
    </MainItem>
  </ItemGroup>
  <ItemGroup>
    <MainItem>
      <Key>Bridger</Key>
      <Title>Lt.</Title>
      <Forenames>G. T.</Forenames>
      <Text>(resigns commn., and retains rank of Lt.)</Text>
      <PageNumber>4030</PageNumber>
    </MainItem>
  </ItemGroup>
  <ItemGroup>
    <MainItem>
      <Key>Brigden</Key>
      <Title>Lt.</Title>
      <Forenames>F. L.</Forenames>
      <Text>
        <Honour>D.S.O.</Honour>
      </Text>
      <PageNumber>4668</PageNumber>
    </MainItem>
  </ItemGroup>
  <ItemGroup>
    <MainItem>
      <Key>
        <KeyDitto>___ ___ ___</KeyDitto>
      </Key>
      <Title>Capt.</Title>
      <Forenames>L. R.</Forenames>
      <Text>(rel. commn. in T.F. on appt. to a perm, commn. in R.A.F., and re tains rank of Capt.)</Text>
      <PageNumber>6332</PageNumber>
    </MainItem>
  </ItemGroup>
  <ItemGroup>
    <MainItem>
      <Key>
        <KeyDitto>___ ___ ___</KeyDitto>
      </Key>
      <Title>Lt.</Title>
      <Forenames>W.</Forenames>
      <Text>(restd. to estabt. on ceasing to be empld. with Tank Corps)</Text>
      <PageNumber>6865</PageNumber>
    </MainItem>
  </ItemGroup>
  <ItemGroup>
    <MainItem>
      <Key>Brigham</Key>
      <Title>Capt.</Title>
      <Forenames>K. B.</Forenames>
      <Text>(resigns commn., and retains ranK of Capt.)</Text>
      <PageNumber>4812</PageNumber>
    </MainItem>
  </ItemGroup>
  <ItemGroup>
    <MainItem>
      <Key>Bright</Key>
      <Title>temp.</Title>
      <Forenames>End</Forenames>
      <Text>Lt. J. A. M. (Adjt., with pay and allces. of Lt,, A. of O., corr. of date) Sub. Not</Text>
      <PageNumber>4824</PageNumber>
    </MainItem>
  </ItemGroup>
  <ItemGroup>
    <MainItem>
      <Key>Brightmore</Key>
      <Title>Lt.</Title>
      <Forenames>J.</Forenames>
      <Text>
        <Honour>G.C.</Honour>
      </Text>
      <PageNumber>6772</PageNumber>
    </MainItem>
  </ItemGroup>
  <ItemGroup>
    <MainItem>
      <Key>Brims</Key>
      <Title>Maj. (Bt, Lt.-Col.)</Title>
      <Forenames>C. W.</Forenames>
      <Text>
        <Honour>M.C.</Honour>
        <Honour>T.D.</Honour>
      </Text>
      <PageNumber>5909</PageNumber>
    </MainItem>
  </ItemGroup>
  <ItemGroup>
    <MainItem>
      <Key>Britcliffe</Key>
      <Title>Capt.</Title>
      <Forenames>F.</Forenames>
      <Text>
        <Honour>M.C.</Honour>
      </Text>
      <PageNumber>4214</PageNumber>
    </MainItem>
  </ItemGroup>
  <ItemGroup>
    <MainItem>
      <Key>Brittain</Key>
      <Title>Lt.</Title>
      <Forenames>E.</Forenames>
      <Text>(restd. to estabt.)</Text>
      <PageNumber>5223</PageNumber>
    </MainItem>
  </ItemGroup>
  <ItemGroup>
    <MainItem>
      <Key>Britten</Key>
      <Title>Capt.</Title>
      <Forenames>W. E.</Forenames>
      <Text>
        <Honour>O.B.E.</Honour>
      </Text>
      <PageNumber>4030</PageNumber>
    </MainItem>
  </ItemGroup>
  <ItemGroup>
    <MainItem>
      <Key>Broadbent</Key>
      <Forenames>End Lt</Forenames>
      <Text>
        <Honour>M.C.</Honour>
      </Text>
      <PageNumber>5353</PageNumber>
    </MainItem>
  </ItemGroup>
  <ItemGroup>
    <MainItem>
      <Key>Broadbridge</Key>
      <Title>2nd Lt. (actg. Capt.)</Title>
      <Text>^ E. L. (rel, actg. rank of Capt. on ceasing to be empld.)</Text>
      <PageNumber>4680</PageNumber>
    </MainItem>
  </ItemGroup>
  <ItemGroup>
    <MainItem>
      <Key>Brock</Key>
      <Title>Lt.</Title>
      <Forenames>E. F.</Forenames>
      <Text>(restd. to estabt,</Text>
      <PageNumber>4669</PageNumber>
    </MainItem>
  </ItemGroup>
  <ItemGroup>
    <MainItem>
      <Key>Brockbank</Key>
      <Title>Capt.</Title>
      <Forenames>G. R.</Forenames>
      <Text>,, M.C (resigns oommn., and retains rank of Capt.)</Text>
      <PageNumber>6688</PageNumber>
    </MainItem>
  </ItemGroup>
  <ItemGroup>
    <MainItem>
      <Key>Brockman</Key>
      <Forenames>Lt</Forenames>
      <Text>
        <Honour>M.C.</Honour>
      </Text>
      <PageNumber>5078</PageNumber>
    </MainItem>
  </ItemGroup>
  <ItemGroup>
    <MainItem>
      <Key>Broderick</Key>
      <Title>Capt.</Title>
      <Forenames>R. A.</Forenames>
      <Text>
        <Honour>M.C.</Honour>
      </Text>
      <PageNumber>5080</PageNumber>
    </MainItem>
  </ItemGroup>
  <ItemGroup>
    <MainItem>
      <Key>Bromley</Key>
      <Title>2nd Lt.</Title>
      <Forenames>B.</Forenames>
      <Text>(Lt.)</Text>
      <PageNumber>4668</PageNumber>
    </MainItem>
  </ItemGroup>
  <ItemGroup>
    <MainItem>
      <Key>Bromley-Wilson</Key>
      <Title>2nd Lt. Sir</Title>
      <Forenames>M.</Forenames>
      <Text>
        <Honour>Bart</Honour>
      </Text>
      <PageNumber>6162</PageNumber>
    </MainItem>
  </ItemGroup>
  <ItemGroup>
    <MainItem>
      <Key>Brooke</Key>
      <Title>Lt.</Title>
      <Forenames>A. C.</Forenames>
      <Text>(restd. to estabt. on ceasing to be empld. with M.G.O.)</Text>
      <PageNumber>6447</PageNumber>
    </MainItem>
  </ItemGroup>
  <ItemGroup>
    <MainItem>
      <Key>
        <KeyDitto>___ ___</KeyDitto>
      </Key>
      <Title>Lt.</Title>
      <Forenames>E. J. S. L.</Forenames>
      <Text>
        <Honour>M.C.</Honour>
      </Text>
      <PageNumber>6857</PageNumber>
    </MainItem>
  </ItemGroup>
  <ItemGroup>
    <MainItem>
      <Key>
        <KeyDitto>— ___ ___</KeyDitto>
      </Key>
      <Title>2nd Lt.</Title>
      <Forenames>J.</Forenames>
      <Text>(Lt.)</Text>
      <PageNumber>4450</PageNumber>
    </MainItem>
  </ItemGroup>
  <ItemGroup>
    <MainItem>
      <Key>Brookes</Key>
      <Title>Lt.</Title>
      <Forenames>P. D.</Forenames>
      <Text>(resigns commin. and retains rank of Lt.)</Text>
      <PageNumber>5446</PageNumber>
    </MainItem>
  </ItemGroup>
  <ItemGroup>
    <MainItem>
      <Key>Brooks</Key>
      <Title>Capt.</Title>
      <Forenames>C. J.</Forenames>
      <Text>
        <Honour>G.C.</Honour>
      </Text>
      <PageNumber>5920</PageNumber>
    </MainItem>
  </ItemGroup>
  <ItemGroup>
    <MainItem>
      <Key>
        <KeyDitto>___ ___</KeyDitto>
      </Key>
      <Title>Lt.</Title>
      <Forenames>E. W.</Forenames>
      <Text>
        <Honour>G.C.</Honour>
      </Text>
      <PageNumber>7084</PageNumber>
    </MainItem>
  </ItemGroup>
  <ItemGroup>
    <MainItem>
      <Key>
        <KeyDitto>___ ___</KeyDitto>
      </Key>
      <Title>Lt. (actg. Capt., without pay and allces.)</Title>
      <Forenames>N. B.</Forenames>
      <Text>
        <Honour>M.C.</Honour>
      </Text>
      <PageNumber>5212</PageNumber>
    </MainItem>
  </ItemGroup>
  <ItemGroup>
    <MainItem>
      <Key>
        <KeyDitto>___ —</KeyDitto>
      </Key>
      <Title>Lt.</Title>
      <Forenames>R. B. D.</Forenames>
      <Text>(restd. to estabt.)</Text>
      <PageNumber>4813</PageNumber>
    </MainItem>
  </ItemGroup>
  <ItemGroup>
    <MainItem>
      <Key>
        <KeyDitto>___ ___ ___ .</KeyDitto>
      </Key>
      <Forenames>Capt</Forenames>
      <Text>, W. N. (resigns commn and retains rank of Capt, .. -</Text>
      <PageNumber>6969</PageNumber>
    </MainItem>
  </ItemGroup>
  <ItemGroup>
    <MainItem>
      <Key>Broom</Key>
      <Title>2nd Lt. (temp. Lt.)</Title>
      <Forenames>C. G. M.</Forenames>
      <Text>(rel. commn., and granted rank of Lt.)</Text>
      <PageNumber>6679</PageNumber>
    </MainItem>
  </ItemGroup>
  <ItemGroup>
    <MainItem>
      <Key>Broomfield</Key>
      <Title>2nd Lt.</Title>
      <Forenames>H. F.</Forenames>
      <Text>(Lt.)</Text>
      <PageNumber>6171</PageNumber>
    </MainItem>
  </ItemGroup>
  <ItemGroup>
    <MainItem>
      <Key>Browett</Key>
      <Forenames>End Lt</Forenames>
      <Text>, J. G. S. (Lt.)</Text>
      <PageNumber>4420</PageNumber>
    </MainItem>
  </ItemGroup>
  <ItemGroup>
    <MainItem>
      <Key>Brown</Key>
      <Title>temp. Lt.</Title>
      <Forenames>A.</Forenames>
      <Text>
        <Honour>M.C.</Honour>
      </Text>
      <PageNumber>4692</PageNumber>
    </MainItem>
  </ItemGroup>
  <ItemGroup>
    <MainItem>
      <Key>
        <KeyDitto>___ ___ ___ ___ .</KeyDitto>
      </Key>
      <Title>2nd Lt.</Title>
      <Text>. A. (Gord. Highrs.)</Text>
      <PageNumber>6331</PageNumber>
    </MainItem>
  </ItemGroup>
  <ItemGroup>
    <MainItem>
      <Key>
        <KeyDitto>___ ___ ___</KeyDitto>
      </Key>
      <Title>Lt.</Title>
      <Text>
        <Honour>M.C.</Honour>
      </Text>
      <PageNumber>6423</PageNumber>
    </MainItem>
  </ItemGroup>
  <ItemGroup>
    <MainItem>
      <Key>
        <KeyDitto>___ ___ ___</KeyDitto>
      </Key>
      <Title>Lt.</Title>
      <Forenames>A. P.</Forenames>
      <Text>(trd. to R.A.S.C., T K R )</Text>
      <PageNumber>6666</PageNumber>
    </MainItem>
  </ItemGroup>
  <KeyDitto>___ ___ ___</KeyDitto>
  <ItemGroup>
    <MainItem>
      <Key>
        <KeyDitto>___ ___</KeyDitto>
      </Key>
      <Title>Lt.</Title>
      <Forenames>C.</Forenames>
      <Text>
        <Honour>M.C.</Honour>
      </Text>
      <PageNumber>6160</PageNumber>
    </MainItem>
  </ItemGroup>
  <ItemGroup>
    <MainItem>
      <Key>
        <KeyDitto>___ ___ .</KeyDitto>
      </Key>
      <Title>Maj.</Title>
      <Forenames>C. R.</Forenames>
      <Text>(3rd E. Lanes. Bde.) (trd. to T.F.R.)</Text>
      <PageNumber>4569</PageNumber>
    </MainItem>
  </ItemGroup>
  <ItemGroup>
    <MainItem>
      <Key>
        <KeyDitto>___ ___ .</KeyDitto>
      </Key>
      <Forenames>Lt</Forenames>
      <Text>
        <Honour>M.C.</Honour>
        <Honour>G.C</Honour>
      </Text>
      <PageNumber>5683</PageNumber>
    </MainItem>
  </ItemGroup>
  <ItemGroup>
    <MainItem>
      <Key>
        <KeyDitto>___ ___ ___ ___</KeyDitto>
      </Key>
      <Title>Lt. (actg. Maj.)</Title>
      <Forenames>D.</Forenames>
      <Text>(rel. actg. rank of Maj.)</Text>
      <PageNumber>5078</PageNumber>
    </MainItem>
  </ItemGroup>
  <ItemGroup>
    <MainItem>
      <Key>
        <KeyDitto>___ ___</KeyDitto>
      </Key>
      <Forenames>Lt</Forenames>
      <Text>
        <Honour>G.C.</Honour>
      </Text>
      <PageNumber>5682</PageNumber>
    </MainItem>
  </ItemGroup>
  <ItemGroup>
    <MainItem>
      <Key>
        <KeyDitto>___ ___</KeyDitto>
      </Key>
      <Title>2nd Lt.</Title>
      <Forenames>H. G.</Forenames>
      <Text>(Lt.) „</Text>
      <PageNumber>4450</PageNumber>
    </MainItem>
  </ItemGroup>
  <KeyDitto>___ ___</KeyDitto>
  <ItemGroup>
    <MainItem>
      <Key>
        <KeyDitto>___</KeyDitto>
      </Key>
      <Title>Maj.</Title>
      <Forenames>J. H.</Forenames>
      <Text>(resigns commn., and retains rank of Maj., with permission of wear uniform)</Text>
      <PageNumber>5703</PageNumber>
    </MainItem>
  </ItemGroup>
  <ItemGroup>
    <MainItem>
      <Key>
        <KeyDitto>___ ___</KeyDitto>
      </Key>
      <Title>Maj.</Title>
      <Forenames>K. A.</Forenames>
      <Text>
        <Honour>D.S.O.</Honour>
      </Text>
      <PageNumber>6169</PageNumber>
    </MainItem>
  </ItemGroup>
  <ItemGroup>
    <MainItem>
      <Key>
        <KeyDitto>___ ___ ___</KeyDitto>
      </Key>
      <Title>Lt.</Title>
      <Forenames>L. G.</Forenames>
      <Text>(rel. appt. of Adjt.. A. of 0.), Sub. Not</Text>
      <PageNumber>4439</PageNumber>
    </MainItem>
  </ItemGroup>
  <ItemGroup>
    <MainItem>
      <Key>
        <KeyDitto>___ ___</KeyDitto>
      </Key>
      <Text>2nd Lt, L. S. (Lt.)</Text>
      <PageNumber>5343</PageNumber>
    </MainItem>
  </ItemGroup>
  <ItemGroup>
    <MainItem>
      <Key>
        <KeyDitto>___ ___</KeyDitto>
      </Key>
      <Title>Lt. (actg. Capt.)</Title>
      <Forenames>R</Forenames>
      <Text>, A. (rel. actg. rank of Cant, on ceasing to comd. a Co.)</Text>
      <PageNumber>4031</PageNumber>
    </MainItem>
  </ItemGroup>
  <ItemGroup>
    <MainItem>
      <Key>
        <KeyDitto>___ ___ ___</KeyDitto>
      </Key>
      <Title>Lt.</Title>
      <Text>-W. (rel. commn. on acc. of ill-health caused by wounds, and retains rank of Lt.)</Text>
      <PageNumber>5717</PageNumber>
    </MainItem>
  </ItemGroup>
  <ItemGroup>
    <MainItem>
      <Key>
        <KeyDitto>___</KeyDitto>
      </Key>
      <Title>Lt.</Title>
      <Forenames>W. J.</Forenames>
      <Text>
        <Honour>M.C.</Honour>
      </Text>
      <PageNumber>6772</PageNumber>
    </MainItem>
  </ItemGroup>
  <ItemGroup>
    <MainItem>
      <Key>Browne</Key>
      <Title>Dame</Title>
      <Forenames>S. J.</Forenames>
      <Text>
        <Honour>G.B.E.</Honour>
        <Honour>R.R.C.</Honour>
      </Text>
      <PageNumber>4691</PageNumber>
    </MainItem>
  </ItemGroup>
  <ItemGroup>
    <MainItem>
      <Key>
        <KeyDitto>___ ___</KeyDitto>
      </Key>
      <Title>Capt.</Title>
      <Forenames>W. P.</Forenames>
      <Text>
        <Honour>M.C.</Honour>
      </Text>
      <PageNumber>5353</PageNumber>
    </MainItem>
  </ItemGroup>
  <ItemGroup>
    <MainItem>
      <Key>Brownlie</Key>
      <Title>2nd Lt.</Title>
      <Forenames>W.</Forenames>
      <Text>(Lt.)</Text>
      <PageNumber>4420</PageNumber>
    </MainItem>
  </ItemGroup>
  <ItemGroup>
    <MainItem>
      <Key>Bruce</Key>
      <Title>2nd Lt.</Title>
      <Forenames>A.</Forenames>
      <Text>McK. {lit.)</Text>
      <PageNumber>5213</PageNumber>
    </MainItem>
  </ItemGroup>
  <ItemGroup>
    <MainItem>
      <Key>
        <KeyDitto>___ ___</KeyDitto>
      </Key>
      <Title>Maj.</Title>
      <Forenames>G. A.</Forenames>
      <Text>
        <Honour>T.D.</Honour>
      </Text>
      <PageNumber>6986</PageNumber>
    </MainItem>
  </ItemGroup>
  <ItemGroup>
    <MainItem>
      <Key>
        <KeyDitto>___ ___</KeyDitto>
      </Key>
      <Title>Maj.</Title>
      <Forenames>J.</Forenames>
      <Text>(resigns commn., and retains rank of Maj.,_ with permission to wear uniform)</Text>
      <PageNumber>6970</PageNumber>
    </MainItem>
  </ItemGroup>
  <ItemGroup>
    <MainItem>
      <Key>
        <KeyDitto>___ ___</KeyDitto>
      </Key>
      <Title>Lt.-Col.</Title>
      <Forenames>B</Forenames>
      <Text>
        <Honour>D.S.O.</Honour>
        <Honour>T.D.</Honour>
      </Text>
      <PageNumber>6557</PageNumber>
    </MainItem>
  </ItemGroup>
  <ItemGroup>
    <MainItem>
      <Key>Bruce-Gardyne</Key>
      <Title>Lt.</Title>
      <Forenames>I. M.</Forenames>
      <Text>
        <Honour>M.C.</Honour>
      </Text>
      <PageNumber>6557</PageNumber>
    </MainItem>
  </ItemGroup>
  <ItemGroup>
    <MainItem>
      <Key>Bryant</Key>
      <Title>Lt.</Title>
      <Forenames>J.</Forenames>
      <Text>(rel. commn. on acc. of ill-health caused by wounds, and retains rank of Lt.)</Text>
      <PageNumber>4319</PageNumber>
    </MainItem>
  </ItemGroup>
  <ItemGroup>
    <MainItem>
      <Key>
        <KeyDitto>___ ___</KeyDitto>
      </Key>
      <Title>2nd Lt.</Title>
      <Forenames>J. W.</Forenames>
      <Text>(Lt.)</Text>
      <PageNumber>4318</PageNumber>
    </MainItem>
  </ItemGroup>
  <ItemGroup>
    <MainItem>
      <Key>
        <KeyDitto>___ ___</KeyDitto>
      </Key>
      <Title>2nd Lt.</Title>
      <Forenames>T. S.</Forenames>
      <Text>(Lt.)</Text>
      <PageNumber>6152</PageNumber>
    </MainItem>
  </ItemGroup>
  <ItemGroup>
    <MainItem>
      <Key>Bryden</Key>
      <Title>2nd Lt.</Title>
      <Forenames>G. A.</Forenames>
      <Text>
        <Honour>M.C.</Honour>
      </Text>
      <PageNumber>4420</PageNumber>
    </MainItem>
  </ItemGroup>
  <ItemGroup>
    <MainItem>
      <Key>Brymer</Key>
      <Title>Capt.</Title>
      <Forenames>G.</Forenames>
      <Text>
        <Honour>M.C.</Honour>
      </Text>
      <PageNumber>6670</PageNumber>
    </MainItem>
  </ItemGroup>
  <ItemGroup>
    <MainItem>
      <Key>Bryson</Key>
      <Title>2nd Lt.</Title>
      <Forenames>A.</Forenames>
      <Text>(Lt.)</Text>
      <PageNumber>5343</PageNumber>
    </MainItem>
  </ItemGroup>
  <ItemGroup>
    <MainItem>
      <Key>Buchanan</Key>
      <Title>2nd Lt.</Title>
      <Forenames>C.</Forenames>
      <Text>(trd. to T.F.R.)</Text>
      <PageNumber>7086</PageNumber>
    </MainItem>
  </ItemGroup>
  <ItemGroup>
    <MainItem>
      <Key>
        <KeyDitto>___ ___ ___</KeyDitto>
      </Key>
      <Title>Capt.</Title>
      <Forenames>E. C.</Forenames>
      <Text>(trd. to T.F.R.)</Text>
      <PageNumber>7086</PageNumber>
    </MainItem>
  </ItemGroup>
  <ItemGroup>
    <MainItem>
      <Key>
        <KeyDitto>___ ___ ___</KeyDitto>
      </Key>
      <Title>Lt.</Title>
      <Forenames>H. B.</Forenames>
      <Text>(resigns commn. and retains rank of Lt.)</Text>
      <PageNumber>5214</PageNumber>
    </MainItem>
    <SubItem>
      <Text>Resigns conxmn., and retains rank of Lt., Sub. Not</Text>
      <PageNumber>5474</PageNumber>
    </SubItem>
  </ItemGroup>
  <ItemGroup>
    <MainItem>
      <Key>
        <KeyDitto>___ ___</KeyDitto>
      </Key>
      <Title>Capt.</Title>
      <Forenames>G. B.</Forenames>
      <Text>, M.B. {resigns commn., and granted rank of Maj.)</Text>
      <PageNumber>5344</PageNumber>
    </MainItem>
  </ItemGroup>
  <ItemGroup>
    <MainItem>
      <Key>
        <KeyDitto>___ ___ ___</KeyDitto>
      </Key>
      <Title>Capt.</Title>
      <Forenames>J.</Forenames>
      <Text>
        <Honour>M.C.</Honour>
      </Text>
      <PageNumber>6023</PageNumber>
    </MainItem>
  </ItemGroup>
  <ItemGroup>
    <MainItem>
      <Key>
        <KeyDitto>___ ___</KeyDitto>
      </Key>
      <Title>2nd Lt.</Title>
      <Forenames>J. F.</Forenames>
      <Text>
        <Honour>D.C.M.</Honour>
      </Text>
      <PageNumber>4680</PageNumber>
    </MainItem>
  </ItemGroup>
  <ItemGroup>
    <MainItem>
      <Key>
        <KeyDitto>___ ___</KeyDitto>
      </Key>
      <Title>Capt.</Title>
      <Forenames>K. G.</Forenames>
      <Text>
        <Honour>M.C.</Honour>
      </Text>
      <PageNumber>4440</PageNumber>
    </MainItem>
  </ItemGroup>
  <ItemGroup>
    <MainItem>
      <Key>
        <KeyDitto>___</KeyDitto>
      </Key>
      <Title>Lt.</Title>
      <Forenames>L. G.</Forenames>
      <Text>(resigns oommn., and retains rank of Lt.)</Text>
      <PageNumber>4340</PageNumber>
    </MainItem>
  </ItemGroup>
  <ItemGroup>
    <MainItem>
      <Key>Buck</Key>
      <Title>2nd Lt.</Title>
      <Forenames>H. J.</Forenames>
      <Text>(Lt.)</Text>
      <PageNumber>5474</PageNumber>
    </MainItem>
  </ItemGroup>
  <ItemGroup>
    <MainItem>
      <Key>
        <KeyDitto>___ ___</KeyDitto>
      </Key>
      <Title>Lt.</Title>
      <Forenames>W. J.</Forenames>
      <Text>
        <Honour>G.C.</Honour>
      </Text>
      <PageNumber>6556</PageNumber>
    </MainItem>
  </ItemGroup>
  <ItemGroup>
    <MainItem>
      <Key>Buckler</Key>
      <Title>2nd Lt.</Title>
      <Forenames>W. H.</Forenames>
      <Text>(Lt.)</Text>
      <PageNumber>4955</PageNumber>
    </MainItem>
  </ItemGroup>
  <ItemGroup>
    <MainItem>
      <Key>Buckley</Key>
      <Title>2nd Lt.</Title>
      <Forenames>H. E.</Forenames>
      <Text>(Lt.)</Text>
      <PageNumber>5228</PageNumber>
    </MainItem>
  </ItemGroup>
  <ItemGroup>
    <MainItem>
      <Key>
        <KeyDitto>___ ___</KeyDitto>
      </Key>
      <Title>2nd Lt.</Title>
      <Forenames>J. E.</Forenames>
      <Text>(Lt.)</Text>
      <PageNumber>5920</PageNumber>
    </MainItem>
  </ItemGroup>
  <ItemGroup>
    <MainItem>
      <Key>Bullivant</Key>
      <Title>Lt.</Title>
      <Forenames>W.</Forenames>
      <Text>(resigns commn., and retains rank of Lt.)</Text>
      <PageNumber>4214</PageNumber>
    </MainItem>
  </ItemGroup>
  <ItemGroup>
    <MainItem>
      <Key>Bulmer</Key>
      <Title>Capt.</Title>
      <Forenames>C.</Forenames>
      <Text>(trd. to T.F.R.)</Text>
      <PageNumber>7085</PageNumber>
    </MainItem>
  </ItemGroup>
  <ItemGroup>
    <MainItem>
      <Key>Bulteel</Key>
      <Title>Capt.</Title>
      <Forenames>J. C</Forenames>
      <Text>
        <Honour>D.S.O.</Honour>
        <Honour>M.C.</Honour>
        <Honour>G.C.</Honour>
      </Text>
      <PageNumber>5469</PageNumber>
    </MainItem>
  </ItemGroup>
  <ItemGroup>
    <MainItem>
      <Key>Bunting</Key>
      <Title>Capt.</Title>
      <Text>
        <Honour>M.D.</Honour>
      </Text>
      <PageNumber>5921</PageNumber>
    </MainItem>
  </ItemGroup>
  <ItemGroup>
    <MainItem>
      <Key>Buroh</Key>
      <Title>Lt.</Title>
      <Forenames>C. M.</Forenames>
      <Text>
        <Honour>G.C.</Honour>
      </Text>
      <PageNumber>5460</PageNumber>
    </MainItem>
  </ItemGroup>
  <ItemGroup>
    <MainItem>
      <Key>Burditt</Key>
      <Title>Lt.</Title>
      <Forenames>H.</Forenames>
      <Text>
        <Honour>M.C.</Honour>
        <Honour>G.C.</Honour>
      </Text>
      <PageNumber>7084</PageNumber>
    </MainItem>
  </ItemGroup>
  <ItemGroup>
    <MainItem>
      <Key>Burfield</Key>
      <Title>Lt.</Title>
      <Forenames>S. T.</Forenames>
      <Text>(resigns commn., and granted rank of Ca.pt.)</Text>
      <PageNumber>5703</PageNumber>
    </MainItem>
    <SubItem>
      <Text>2nd Lt. A. ((Lt.)</Text>
      <PageNumber>4813</PageNumber>
    </SubItem>
  </ItemGroup>
  <ItemGroup>
    <MainItem>
      <Key>
        <KeyDitto>___</KeyDitto>
      </Key>
      <Text>JA. F. (restd. to estabt.)</Text>
      <PageNumber>6670</PageNumber>
    </MainItem>
  </ItemGroup>
  <ItemGroup>
    <MainItem>
      <Key>
        <KeyDitto>___ ___</KeyDitto>
      </Key>
      <Title>Capt.</Title>
      <Forenames>R.</Forenames>
      <Text>
        <Honour>D.S.O.</Honour>
        <Honour>M.C.</Honour>
      </Text>
      <PageNumber>5462</PageNumber>
    </MainItem>
  </ItemGroup>
  <ItemGroup>
    <MainItem>
      <Key>Burkitt</Key>
      <Title>2nd Lt.</Title>
      <Forenames>T. W.</Forenames>
      <Text>(Lt.)</Text>
      <PageNumber>4977</PageNumber>
    </MainItem>
  </ItemGroup>
  <ItemGroup>
    <MainItem>
      <Key>Burlton</Key>
      <Title>Lt.</Title>
      <Forenames>F. A.</Forenames>
      <Text>
        <Honour>G.C.</Honour>
      </Text>
      <PageNumber>5460</PageNumber>
    </MainItem>
  </ItemGroup>
  <ItemGroup>
    <MainItem>
      <Key>Burman</Key>
      <Title>Lt.</Title>
      <Forenames>F. S.</Forenames>
      <Text>(resigns oommn and retains rank of Lt.)</Text>
      <PageNumber>6984</PageNumber>
    </MainItem>
  </ItemGroup>
  <ItemGroup>
    <MainItem>
      <Key>Burn</Key>
      <Title>Capt.</Title>
      <Forenames>R. O. W.</Forenames>
      <Text>
        <Honour>G.C.</Honour>
      </Text>
      <PageNumber>6151</PageNumber>
    </MainItem>
  </ItemGroup>
  <ItemGroup>
    <MainItem>
      <Key>Burne</Key>
      <Title>Maj.</Title>
      <Forenames>S. F.</Forenames>
      <Text>
        <Honour>D.S.O.</Honour>
      </Text>
      <PageNumber>5716</PageNumber>
    </MainItem>
  </ItemGroup>
  <ItemGroup>
    <MainItem>
      <Key>Burnham</Key>
      <Title>Lt.</Title>
      <Forenames>G. K.</Forenames>
      <Text>(resigns commn., and granted rank of Capt.)</Text>
      <PageNumber>5683</PageNumber>
    </MainItem>
  </ItemGroup>
  <ItemGroup>
    <MainItem>
      <Key>Burns</Key>
      <Title>Capt.</Title>
      <Forenames>J. G.</Forenames>
      <Text>(resigns commn., and retains rank of Capt.}</Text>
      <PageNumber>6969</PageNumber>
    </MainItem>
  </ItemGroup>
  <ItemGroup>
    <MainItem>
      <Key>
        <KeyDitto>___ ___</KeyDitto>
      </Key>
      <Title>Lt. (actg. Capt., R.A.)</Title>
      <Forenames>M.</Forenames>
      <Text>(restd. to estabt.)</Text>
      <PageNumber>4213</PageNumber>
    </MainItem>
  </ItemGroup>
  <ItemGroup>
    <MainItem>
      <Key>
        <KeyDitto>___ ___</KeyDitto>
      </Key>
      <Title>Lt.</Title>
      <Forenames>R. P.</Forenames>
      <Text>(restd. to estabt.)</Text>
      <PageNumber>4955</PageNumber>
    </MainItem>
  </ItemGroup>
  <ItemGroup>
    <MainItem>
      <Key>Burris-Lindow</Key>
      <Title>Capt.</Title>
      <Forenames>M. H. J</Forenames>
      <Text>
        <Honour>M.C.</Honour>
      </Text>
      <PageNumber>4966</PageNumber>
    </MainItem>
  </ItemGroup>
  <ItemGroup>
    <MainItem>
      <Key>
        <KeyDitto>-</KeyDitto>
      </Key>
      <Forenames>Burnyeat</Forenames>
      <Text>
        <Honour>D.S.O.</Honour>
        <Honour>T.D.</Honour>
      </Text>
      <PageNumber>6023</PageNumber>
    </MainItem>
  </ItemGroup>
  <ItemGroup>
    <MainItem>
      <Key>Burr</Key>
      <Title>Lt.</Title>
      <Forenames>D. M.</Forenames>
      <Text>
        <Honour>M.C.</Honour>
      </Text>
      <PageNumber>4339</PageNumber>
    </MainItem>
  </ItemGroup>
  <ItemGroup>
    <MainItem>
      <Key>Burrell</Key>
      <Title>Lt.</Title>
      <Text>
        <Honour>O.B.E.</Honour>
      </Text>
      <PageNumber>4668</PageNumber>
    </MainItem>
    <SubItem>
      <Text>Lt.-Col.</Text>
      <PageNumber>4668</PageNumber>
    </SubItem>
  </ItemGroup>
  <ItemGroup>
    <MainItem>
      <Key>Burroughs</Key>
      <Title>Lt. (actg. Capt.)</Title>
      <Text>
        <Honour>M.C.</Honour>
      </Text>
      <PageNumber>4680</PageNumber>
    </MainItem>
  </ItemGroup>
  <ItemGroup>
    <MainItem>
      <Key>Burrows</Key>
      <Title>Lt.</Title>
      <Forenames>H. R.</Forenames>
      <Text>
        <Honour>M.C.</Honour>
      </Text>
      <PageNumber>5461</PageNumber>
    </MainItem>
  </ItemGroup>
  <ItemGroup>
    <MainItem>
      <Key>Burt</Key>
      <Title>Qrmr. and Capt.</Title>
      <Forenames>C. A.</Forenames>
      <Text>(resigns commn.)</Text>
      <PageNumber>5444</PageNumber>
    </MainItem>
  </ItemGroup>
  <ItemGroup>
    <MainItem>
      <Key>Burton</Key>
      <Title>2nd Lt.</Title>
      <Forenames>B.</Forenames>
      <Text>
        <Honour>M.M.</Honour>
      </Text>
      <PageNumber>5212</PageNumber>
    </MainItem>
  </ItemGroup>
  <ItemGroup>
    <MainItem>
      <Key>
        <KeyDitto>___ ___</KeyDitto>
      </Key>
      <Title>2nd Lt.</Title>
      <Forenames>J. W.</Forenames>
      <Text>(Lt.)</Text>
      <PageNumber>4955</PageNumber>
    </MainItem>
  </ItemGroup>
  <ItemGroup>
    <MainItem>
      <Key>
        <KeyDitto>___ ___ ___</KeyDitto>
      </Key>
      <Title>Lt.</Title>
      <Forenames>L. F.</Forenames>
      <Text>
        <Honour>M.C.</Honour>
        <Honour>M.M.</Honour>
      </Text>
      <PageNumber>6312</PageNumber>
    </MainItem>
  </ItemGroup>
  <ItemGroup>
    <MainItem>
      <Key>
        <KeyDitto>___ ___</KeyDitto>
      </Key>
      <Title>Lt.</Title>
      <Forenames>W. F.</Forenames>
      <Text>{trd. to T.F.R.)</Text>
      <PageNumber>7086</PageNumber>
    </MainItem>
  </ItemGroup>
  <ItemGroup>
    <MainItem>
      <Key>Burtt</Key>
      <Text>.2nd Lt. V. S. (Lt.)</Text>
      <PageNumber>4978</PageNumber>
    </MainItem>
  </ItemGroup>
  <ItemGroup>
    <MainItem>
      <Key>Bury</Key>
      <Title>Maj.</Title>
      <Forenames>W. E. G. L.</Forenames>
      <Text>
        <Honour>M.C.</Honour>
      </Text>
      <PageNumber>6670</PageNumber>
    </MainItem>
  </ItemGroup>
  <ItemGroup>
    <MainItem>
      <Key>Busby</Key>
      <Title>2nd Lt.</Title>
      <Forenames>H.</Forenames>
      <Text>(Lt.)</Text>
      <PageNumber>5919</PageNumber>
    </MainItem>
  </ItemGroup>
  <ItemGroup>
    <MainItem>
      <Key>Buscall</Key>
      <Title>2nd Lt.</Title>
      <Forenames>F. W.</Forenames>
      <Text>(Lt.)</Text>
      <PageNumber>5473</PageNumber>
    </MainItem>
  </ItemGroup>
  <ItemGroup>
    <MainItem>
      <Key>Bushell</Key>
      <Title>Lt.</Title>
      <Forenames>E. R.</Forenames>
      <Text>(Maj., T.F.R.)</Text>
      <PageNumber>6435</PageNumber>
    </MainItem>
  </ItemGroup>
  <ItemGroup>
    <MainItem>
      <Key>
        <KeyDitto>___ ___</KeyDitto>
      </Key>
      <Title>Lt.</Title>
      <Forenames>R. R.</Forenames>
      <Text>
        <Honour>M.M.</Honour>
        <Honour>G.C.</Honour>
      </Text>
      <PageNumber>5909</PageNumber>
    </MainItem>
  </ItemGroup>
  <ItemGroup>
    <MainItem>
      <Key>Bussell</Key>
      <Title>2nd Lt.</Title>
      <Forenames>G. R.</Forenames>
      <Text>(Lt.)</Text>
      <PageNumber>5446</PageNumber>
    </MainItem>
    <SubItem>
      <Text>Lt. J. (rel. commn. in T.F. .oh appt. to a perm, commn. in R.A.F., and retains rank of Lt.) ... ..;</Text>
      <PageNumber>6160</PageNumber>
    </SubItem>
  </ItemGroup>
  <ItemGroup>
    <MainItem>
      <Key>Butcher</Key>
      <Title>Lt. (actg. Maj.)</Title>
      <Forenames>A.</Forenames>
      <Text>(rel. actg. rank of Maj.)</Text>
      <PageNumber>5078</PageNumber>
    </MainItem>
  </ItemGroup>
  <ItemGroup>
    <MainItem>
      <Key>Butler</Key>
      <Title>Capt.</Title>
      <Forenames>A. W.</Forenames>
      <Text>
        <Honour>G.C.</Honour>
      </Text>
      <PageNumber>5919</PageNumber>
    </MainItem>
    <SubItem>
      <Text>Trd. to T.F.R</Text>
      <PageNumber>7086</PageNumber>
    </SubItem>
  </ItemGroup>
  <ItemGroup>
    <MainItem>
      <Key>
        <KeyDitto>___ ___ ___</KeyDitto>
      </Key>
      <Title>Lt. (actg. Capt.)</Title>
      <Forenames>G. A.</Forenames>
      <Text>(rel. actg. rank of Capt. on ceasing to comd. a Co.), Sub. Not</Text>
      <PageNumber>5580</PageNumber>
    </MainItem>
  </ItemGroup>
  <ItemGroup>
    <MainItem>
      <Key>
        <KeyDitto>___ ___</KeyDitto>
      </Key>
      <Title>Capt.</Title>
      <Forenames>J. D.</Forenames>
      <Text>
        <Honour>M.B.E.</Honour>
      </Text>
      <PageNumber>4318</PageNumber>
    </MainItem>
  </ItemGroup>
  <ItemGroup>
    <MainItem>
      <Key>
        <KeyDitto>___ ___</KeyDitto>
      </Key>
      <Title>2nd Lt.</Title>
      <Forenames>L.</Forenames>
      <Text>{Lt., and rem. seed. R.A.F.)</Text>
      <PageNumber>4680</PageNumber>
    </MainItem>
  </ItemGroup>
  <ItemGroup>
    <MainItem>
      <Key>
        <KeyDitto>___ ___ ___ ___ ___</KeyDitto>
      </Key>
      <Title>2nd Lt.</Title>
      <Forenames>S. J.</Forenames>
      <Text>(Lt.)</Text>
      <PageNumber>5079</PageNumber>
    </MainItem>
  </ItemGroup>
  <ItemGroup>
    <MainItem>
      <Key>
        <KeyDitto>___ ___ ___</KeyDitto>
      </Key>
      <Title>Lt.</Title>
      <Forenames>T.</Forenames>
      <Text>
        <Honour>G.C.</Honour>
      </Text>
      <PageNumber>6024</PageNumber>
    </MainItem>
  </ItemGroup>
  <KeyDitto>___ ___ ___ ___ ___ ___ ___ ___ ___ ___</KeyDitto>
</Index>

