<?xml version="1.0" encoding="UTF-8"?>
<Index xmlns="http://www.tso.co.uk/assets/namespace/gazetteindex" editionCode="L" page="324" pageID="https://www.thegazette.co.uk/id/London/index/year/1921/volume/4/page/324" pagePDF="https://www.thegazette.co.uk/London/index/year/1921/volume/4/page/324" pageRDF="https://www.thegazette.co.uk/London/index/year/1921/volume/4/page/324?view=linked-data" type="index" volume="4" year="1921">
  <ItemGroup>
    <MainItem>
      <Key>Battock</Key>
      <Text>; Lt. J. C. (rel. commn., and retains rank of Lt.)</Text>
      <PageNumber>10700</PageNumber>
    </MainItem>
  </ItemGroup>
  <ItemGroup>
    <MainItem>
      <Key>Batty</Key>
      <Title>Lt.</Title>
      <Forenames>E. D. M.</Forenames>
      <Text>(rel. commn., and granted rank of Capt.)</Text>
      <PageNumber>8180</PageNumber>
    </MainItem>
  </ItemGroup>
  <ItemGroup>
    <MainItem>
      <Key>Baty</Key>
      <Title>Lt.</Title>
      <Forenames>C. N.</Forenames>
      <Text>(rel. commn., and retains rank of Lt.)</Text>
      <PageNumber>9131</PageNumber>
    </MainItem>
  </ItemGroup>
  <ItemGroup>
    <MainItem>
      <Key>
        <KeyDitto>___ ___ ___</KeyDitto>
      </Key>
      <Forenames>Reginald Elphinstone</Forenames>
      <Text>, M.C. (Lt., 6th Bn. Northd Fus., late 2nd Lt. (Hon. Lt.) R.A.F.)</Text>
      <PageNumber>8266</PageNumber>
    </MainItem>
  </ItemGroup>
  <ItemGroup>
    <MainItem>
      <Key>Baugh</Key>
      <Title>Lt.</Title>
      <Forenames>F. R.</Forenames>
      <Text>(rel. commn., and retains rank of Lt.)</Text>
      <PageNumber>10348</PageNumber>
    </MainItem>
  </ItemGroup>
  <ItemGroup>
    <MainItem>
      <Key>
        <KeyDitto>___ ___</KeyDitto>
      </Key>
      <Title>Lt.</Title>
      <Forenames>J.</Forenames>
      <Text>(rel. commn., and re' tains rank of Lt.)</Text>
      <PageNumber>10091</PageNumber>
    </MainItem>
  </ItemGroup>
  <ItemGroup>
    <MainItem>
      <Key>
        <KeyDitto>___ ___ ___ ___</KeyDitto>
      </Key>
      <Title>Lt.</Title>
      <Forenames>W. E. C.</Forenames>
      <Text>(rel. commn., and retains rank of Lt.)</Text>
      <PageNumber>10360</PageNumber>
    </MainItem>
  </ItemGroup>
  <ItemGroup>
    <MainItem>
      <Key>Baughan-Russell</Key>
      <Title>Lt.</Title>
      <Forenames>J. F. R.</Forenames>
      <Text>(rel. commn., and retains rank of Lt.)</Text>
      <PageNumber>9143</PageNumber>
    </MainItem>
  </ItemGroup>
  <ItemGroup>
    <MainItem>
      <Key>Baumber</Key>
      <Title>Lt.</Title>
      <Forenames>B.</Forenames>
      <Text>(rel. commn., and retains rank of Lt.)</Text>
      <PageNumber>10206</PageNumber>
    </MainItem>
  </ItemGroup>
  <ItemGroup>
    <MainItem>
      <Key>Bawderi</Key>
      <Title>Capt.</Title>
      <Forenames>A. J. F.</Forenames>
      <Text>(rel. commn., and retains rank of Capt.)</Text>
      <PageNumber>10119</PageNumber>
    </MainItem>
  </ItemGroup>
  <ItemGroup>
    <MainItem>
      <Key>
        <KeyDitto>___</KeyDitto>
      </Key>
      <Title>Capt.</Title>
      <Forenames>M. C.</Forenames>
      <Text>(rel. commn., and retains rank of Capt.)</Text>
      <PageNumber>10227</PageNumber>
    </MainItem>
  </ItemGroup>
  <ItemGroup>
    <MainItem>
      <Key>Bax</Key>
      <Title>Lt.</Title>
      <Forenames>C. E. O.</Forenames>
      <Text>(rel. commn., and granted rank of Capt.)</Text>
      <PageNumber>10443</PageNumber>
    </MainItem>
  </ItemGroup>
  <ItemGroup>
    <MainItem>
      <Key>Baxter</Key>
      <Title>Capt.</Title>
      <Forenames>A.</Forenames>
      <Text>, M.D. (retired, having attained age limit, and granted rankof Lt.-Col.)</Text>
      <PageNumber>10217</PageNumber>
    </MainItem>
  </ItemGroup>
  <ItemGroup>
    <MainItem>
      <Key>
        <KeyDitto>—— ___</KeyDitto>
      </Key>
      <Title>Lt.</Title>
      <Forenames>G. B.</Forenames>
      <Text>(rel. commn., and retains rank of Lt.)</Text>
      <PageNumber>10112</PageNumber>
    </MainItem>
  </ItemGroup>
  <ItemGroup>
    <MainItem>
      <Key>
        <KeyDitto>___ ___</KeyDitto>
      </Key>
      <Title>Lt.</Title>
      <Forenames>H. J.</Forenames>
      <Text>(rel. commn., and retains rank of Lt.)</Text>
      <PageNumber>10461</PageNumber>
    </MainItem>
  </ItemGroup>
  <ItemGroup>
    <MainItem>
      <Key>
        <KeyDitto>___ ___ ___ ___ ___</KeyDitto>
      </Key>
      <Title>Lt.</Title>
      <Forenames>K. C.</Forenames>
      <Text>(rel. commn., and retains rank of Lt.)</Text>
      <PageNumber>10115</PageNumber>
    </MainItem>
  </ItemGroup>
  <ItemGroup>
    <MainItem>
      <Key>
        <KeyDitto>___ ___ ___ ___</KeyDitto>
      </Key>
      <Title>Lt.</Title>
      <Forenames>P.</Forenames>
      <Text>(4th Bn. Loyal R.) (rel. commn., and retains rank of Lt.)</Text>
      <PageNumber>10441</PageNumber>
    </MainItem>
  </ItemGroup>
  <ItemGroup>
    <MainItem>
      <Key>
        <KeyDitto>___ ___ ___</KeyDitto>
      </Key>
      <Text>2nd Lt. P. (T.A. Res. Inf.) (rel. commn., and retains rank of 2nd Lt.)</Text>
      <PageNumber>10701</PageNumber>
    </MainItem>
  </ItemGroup>
  <ItemGroup>
    <MainItem>
      <Key>
        <KeyDitto>___ ___ ___ ___</KeyDitto>
      </Key>
      <Forenames>Lt</Forenames>
      <Text>, R. (rel. commn., and retains rank of Lt.)</Text>
      <PageNumber>9236</PageNumber>
    </MainItem>
  </ItemGroup>
  <ItemGroup>
    <MainItem>
      <Key>
        <KeyDitto>___ ___ ___ ___</KeyDitto>
      </Key>
      <Title>Lt.</Title>
      <Forenames>T.</Forenames>
      <Text>(rel. commn., and retains rank of Lt.)</Text>
      <PageNumber>9774</PageNumber>
    </MainItem>
  </ItemGroup>
  <ItemGroup>
    <MainItem>
      <Key>Bayes</Key>
      <Title>Lt.</Title>
      <Forenames>L. T.</Forenames>
      <Text>(rel. commn., and retains rank of Lt.)</Text>
      <PageNumber>9023</PageNumber>
    </MainItem>
  </ItemGroup>
  <ItemGroup>
    <MainItem>
      <Key>Bayley</Key>
      <Title>Lt.</Title>
      <Forenames>C. A.</Forenames>
      <Text>(rel. commn., and retains rank of Lt.)</Text>
      <PageNumber>9776</PageNumber>
    </MainItem>
  </ItemGroup>
  <ItemGroup>
    <MainItem>
      <Key>
        <KeyDitto>___ ___ ___ ___</KeyDitto>
      </Key>
      <Title>Capt.</Title>
      <Forenames>E. C.</Forenames>
      <Text>(rel. commn., and retains rank of Capt.)</Text>
      <PageNumber>9438</PageNumber>
    </MainItem>
  </ItemGroup>
  <ItemGroup>
    <MainItem>
      <Key>
        <KeyDitto>___ ___ ___ ___</KeyDitto>
      </Key>
      <Title>Lt.</Title>
      <Forenames>F. A.</Forenames>
      <Text>, M.C. (rel. commn., and granted rank of Capt.)</Text>
      <PageNumber>10108</PageNumber>
    </MainItem>
  </ItemGroup>
  <ItemGroup>
    <MainItem>
      <Key>
        <KeyDitto>___ ___ ___ ___ ___</KeyDitto>
      </Key>
      <Title>Lt.</Title>
      <Forenames>H.</Forenames>
      <Text>DE. (rel. commn., and granted rank of Capt.)</Text>
      <PageNumber>8438</PageNumber>
    </MainItem>
  </ItemGroup>
  <ItemGroup>
    <MainItem>
      <Key>
        <KeyDitto>___ ___ ___</KeyDitto>
      </Key>
      <Title>Lt.</Title>
      <Forenames>L. J.</Forenames>
      <Text>(rel. commn., and retainsrank of Lt.)</Text>
      <PageNumber>10215</PageNumber>
    </MainItem>
  </ItemGroup>
  <ItemGroup>
    <MainItem>
      <Key>
        <KeyDitto>___ ___ ___ ___</KeyDitto>
      </Key>
      <Title>Lt.</Title>
      <Forenames>P.</Forenames>
      <Text>(rel. commn., and retains rank of Lt.)</Text>
      <PageNumber>9239</PageNumber>
    </MainItem>
  </ItemGroup>
  <ItemGroup>
    <MainItem>
      <Key>
        <KeyDitto>___ ___ ___ ___</KeyDitto>
      </Key>
      <Title>Lt.</Title>
      <Forenames>S.</Forenames>
      <Text>(rel. comn-.n., and retains rank of Lt.)</Text>
      <PageNumber>9776</PageNumber>
    </MainItem>
  </ItemGroup>
  <ItemGroup>
    <MainItem>
      <Key>Baylis</Key>
      <Title>Lt.</Title>
      <Forenames>B. S. B.</Forenames>
      <Text>(rel. commn., and retains rank of Lt.)</Text>
      <PageNumber>10475</PageNumber>
    </MainItem>
  </ItemGroup>
  <ItemGroup>
    <MainItem>
      <Key>Bayliss</Key>
      <Text>2nd Lt. A. H., M.M. (rel.commn., and retains rank of 2nd Lt.) T</Text>
      <PageNumber>10443</PageNumber>
    </MainItem>
  </ItemGroup>
  <ItemGroup>
    <MainItem>
      <Key>Bayly</Key>
      <Title>Lt.</Title>
      <Forenames>C.</Forenames>
      <Text>(rel. commn., and retains rank of Lt.)</Text>
      <PageNumber>8697</PageNumber>
    </MainItem>
  </ItemGroup>
  <ItemGroup>
    <MainItem>
      <Key>
        <KeyDitto>___ ___ ___</KeyDitto>
      </Key>
      <Title>Lt.</Title>
      <Forenames>C. A.</Forenames>
      <Text>(rel. commn., and retains rank of Lt.)</Text>
      <PageNumber>9236</PageNumber>
    </MainItem>
  </ItemGroup>
  <ItemGroup>
    <MainItem>
      <Key>Bayne</Key>
      <Text>Maj. C. M.,T.DI (rel. commn., and retains rank of Maj., with permission to wear prescribed uniform)</Text>
      <PageNumber>9773</PageNumber>
    </MainItem>
  </ItemGroup>
  <ItemGroup>
    <MainItem>
      <Key>
        <KeyDitto>___ ___ ___</KeyDitto>
      </Key>
      <Title>Lt.</Title>
      <Forenames>W. J.</Forenames>
      <Text>(rel. commn., and retains rank of Lt.)</Text>
      <PageNumber>10699</PageNumber>
    </MainItem>
  </ItemGroup>
  <ItemGroup>
    <MainItem>
      <Key>Baynes</Key>
      <Title>Lt.</Title>
      <Forenames>G. K.</Forenames>
      <Text>(rel. commn., and retains rank of Lt.)</Text>
      <PageNumber>10475</PageNumber>
    </MainItem>
  </ItemGroup>
  <ItemGroup>
    <MainItem>
      <Key>
        <KeyDitto>___ ___ ___ ___</KeyDitto>
      </Key>
      <Title>Lt.</Title>
      <Forenames>H. B.</Forenames>
      <Text>(rel. commn., and retains rank of Lt.)</Text>
      <PageNumber>10573</PageNumber>
    </MainItem>
  </ItemGroup>
  <ItemGroup>
    <MainItem>
      <Key>
        <KeyDitto>___ ___ ___ ___</KeyDitto>
      </Key>
      <Title>Lt.</Title>
      <Forenames>R. C.</Forenames>
      <Text>(rel. commij., and retains rank of Lt.)</Text>
      <PageNumber>10699</PageNumber>
    </MainItem>
  </ItemGroup>
  <ItemGroup>
    <MainItem>
      <Key>Baynes-Smith</Key>
      <Title>Capt.</Title>
      <Forenames>H. W.</Forenames>
      <Text>, M.C. (rel. commn., and retains rank of Capt.)</Text>
      <PageNumber>10703</PageNumber>
    </MainItem>
  </ItemGroup>
  <ItemGroup>
    <MainItem>
      <Key>Bayvel</Key>
      <Title>Lt.</Title>
      <Forenames>J. F.</Forenames>
      <Text>(rel. commn., and retains rank of Lt.)</Text>
      <PageNumber>9774</PageNumber>
    </MainItem>
  </ItemGroup>
  <ItemGroup>
    <MainItem>
      <Key>Bayntun</Key>
      <Title>Lt.</Title>
      <Forenames>R. S. F.</Forenames>
      <Text>(rel. commn., and retains rank of Lt.)</Text>
      <PageNumber>10475</PageNumber>
    </MainItem>
  </ItemGroup>
  <ItemGroup>
    <MainItem>
      <Key>Bazeley</Key>
      <Forenames>Lt</Forenames>
      <Text>.-Col. W. N., T.D. (rcl. commn., and retains rank of Lt.-Col., with permission to wear prescribed uniform)</Text>
      <PageNumber>10577</PageNumber>
    </MainItem>
  </ItemGroup>
  <ItemGroup>
    <MainItem>
      <Key>Bazell</Key>
      <Title>Lt.</Title>
      <Forenames>R.</Forenames>
      <Text>, M.C. (rel. commn., and granted rank of Capt.)</Text>
      <PageNumber>9130</PageNumber>
    </MainItem>
  </ItemGroup>
  <ItemGroup>
    <MainItem>
      <Key>Beach</Key>
      <Title>Capt.</Title>
      <Forenames>B. A.</Forenames>
      <Text>(rel. commn., and retains rank of Capt.)</Text>
      <PageNumber>10358</PageNumber>
    </MainItem>
  </ItemGroup>
  <ItemGroup>
    <MainItem>
      <Key>
        <KeyDitto>___ ___ ___ ___</KeyDitto>
      </Key>
      <Title>Lt.</Title>
      <Forenames>W. J.</Forenames>
      <Text>(rel. commn., and retains rank of Lt.)</Text>
      <PageNumber>9765</PageNumber>
    </MainItem>
  </ItemGroup>
  <ItemGroup>
    <MainItem>
      <Key>Beadle</Key>
      <Title>Capt.</Title>
      <Forenames>H. E.</Forenames>
      <Text>(rel. commn., and retains rank of Capt.)</Text>
      <PageNumber>10702</PageNumber>
    </MainItem>
  </ItemGroup>
  <ItemGroup>
    <MainItem>
      <Key>
        <KeyDitto>___ ___ ___ ___</KeyDitto>
      </Key>
      <Title>Capt.</Title>
      <Forenames>J. C</Forenames>
      <Text>, M.C. (rel. commn., and granted rank of Maj.)</Text>
      <PageNumber>9236</PageNumber>
    </MainItem>
  </ItemGroup>
  <ItemGroup>
    <MainItem>
      <Key>Beakley</Key>
      <Title>Lt.</Title>
      <Forenames>W.</Forenames>
      <Text>(rel. commn., and retains rank of Lt.)</Text>
      <PageNumber>10346</PageNumber>
    </MainItem>
  </ItemGroup>
  <ItemGroup>
    <MainItem>
      <Key>Beal</Key>
      <Title>Lt.</Title>
      <Forenames>H. G.</Forenames>
      <Text>(rel. oommn., and retains rank of Lt.)</Text>
      <PageNumber>9023</PageNumber>
    </MainItem>
  </ItemGroup>
  <ItemGroup>
    <MainItem>
      <Key>
        <KeyDitto>___ ___ ___ ___ ___</KeyDitto>
      </Key>
      <Title>Lt.</Title>
      <Forenames>J.</Forenames>
      <Text>(rel. commn., and retains rank of Lt.)</Text>
      <PageNumber>10357</PageNumber>
    </MainItem>
  </ItemGroup>
  <ItemGroup>
    <MainItem>
      <Key>Beale</Key>
      <Title>Lt.</Title>
      <Forenames>C. T.</Forenames>
      <Text>(rel. commn., and granted rank of Capt.)</Text>
      <PageNumber>10117</PageNumber>
    </MainItem>
  </ItemGroup>
  <ItemGroup>
    <MainItem>
      <Key>
        <KeyDitto>___ ___ ___ .</KeyDitto>
      </Key>
      <Title>Lt.</Title>
      <Forenames>H. H.</Forenames>
      <Text>(rel. commn., and retains rank of Lt.)</Text>
      <PageNumber>10213</PageNumber>
    </MainItem>
  </ItemGroup>
  <ItemGroup>
    <MainItem>
      <Key>
        <KeyDitto>___ ___ ___ ___ ___ —.—</KeyDitto>
      </Key>
      <Title>Capt.</Title>
      <Forenames>R. W.</Forenames>
      <Text>(rel. commn., and retains rank of Capt.)</Text>
      <PageNumber>9123</PageNumber>
    </MainItem>
  </ItemGroup>
  <ItemGroup>
    <MainItem>
      <Key>Beales</Key>
      <Title>Lt.</Title>
      <Forenames>W. L.</Forenames>
      <Text>(rel. commn., and retains rank of Lt.)</Text>
      <PageNumber>10109</PageNumber>
    </MainItem>
  </ItemGroup>
  <ItemGroup>
    <MainItem>
      <Key>Beall</Key>
      <Title>Lt.</Title>
      <Forenames>C.</Forenames>
      <Text>(rel. comnm., and retains rank of Lt.)</Text>
      <PageNumber>10227</PageNumber>
    </MainItem>
  </ItemGroup>
  <ItemGroup>
    <MainItem>
      <Key>Beames</Key>
      <Title>Lt.</Title>
      <Forenames>R.</Forenames>
      <Text>, M.C. (rel. cominn., and granted rank of Capt.)</Text>
      <PageNumber>9226</PageNumber>
    </MainItem>
  </ItemGroup>
  <ItemGroup>
    <MainItem>
      <Key>Beamish</Key>
      <Text>Capt. (Hon. Lt. in Army) E. A. (rel. commn., and retains rank of Capt.)</Text>
      <PageNumber>9774</PageNumber>
    </MainItem>
  </ItemGroup>
  <ItemGroup>
    <MainItem>
      <Key>Bean</Key>
      <Title>Lt.</Title>
      <Forenames>R. W.</Forenames>
      <Text>(rel. commn., and granted rank of Capt.)</Text>
      <PageNumber>10342</PageNumber>
    </MainItem>
  </ItemGroup>
  <ItemGroup>
    <MainItem>
      <Key>
        <KeyDitto>___ ___ ___ ___</KeyDitto>
      </Key>
      <Title>Lt.</Title>
      <Forenames>T. W.</Forenames>
      <Text>(rel. commn., and retains rank of. Lt.)</Text>
      <PageNumber>9881</PageNumber>
    </MainItem>
  </ItemGroup>
  <ItemGroup>
    <MainItem>
      <Key>Beane</Key>
      <Title>Lt.</Title>
      <Forenames>G. A.</Forenames>
      <Text>(rel. commn., and retains rank of Lt.)</Text>
      <PageNumber>9866</PageNumber>
    </MainItem>
  </ItemGroup>
  <ItemGroup>
    <MainItem>
      <Key>Beard</Key>
      <Title>Lt.</Title>
      <Forenames>G. D. M.</Forenames>
      <Text>(rel. commn., and retains rank of Lt.)</Text>
      <PageNumber>10230</PageNumber>
    </MainItem>
  </ItemGroup>
  <ItemGroup>
    <MainItem>
      <Key>
        <KeyDitto>___ ___ ___ ___</KeyDitto>
      </Key>
      <Title>Lt.</Title>
      <Forenames>H.</Forenames>
      <Text>(rel. commn., and retains rank of Lt.)</Text>
      <PageNumber>10707</PageNumber>
    </MainItem>
  </ItemGroup>
  <ItemGroup>
    <MainItem>
      <Key>
        <KeyDitto>___ ___ ___ ___</KeyDitto>
      </Key>
      <Title>Lt.</Title>
      <Forenames>H. E.</Forenames>
      <Text>(rel. commn., and retains rank of Lt.)</Text>
      <PageNumber>10204</PageNumber>
    </MainItem>
  </ItemGroup>
  <ItemGroup>
    <MainItem>
      <Key>
        <KeyDitto>___ ___ ___</KeyDitto>
      </Key>
      <Title>Lt.</Title>
      <Forenames>H. G.</Forenames>
      <Text>(rel. commn., and retains rank of Lt.)</Text>
      <PageNumber>10440</PageNumber>
    </MainItem>
  </ItemGroup>
  <ItemGroup>
    <MainItem>
      <Key>
        <KeyDitto>___ ___ ___ ___ ___</KeyDitto>
      </Key>
      <Title>Lt.</Title>
      <Forenames>J. L.</Forenames>
      <Text>(trd. to T.A. Res., Regtl. List, 7th Bn., Cheshire R., from A. Cyclist Corps) (T.A.)</Text>
      <PageNumber>9620</PageNumber>
    </MainItem>
  </ItemGroup>
  <ItemGroup>
    <MainItem>
      <Key>
        <KeyDitto>___ ___</KeyDitto>
      </Key>
      <Title>Lt.</Title>
      <Forenames>L. K.</Forenames>
      <Text>(rel. oommn., and retains rank of Lt.)</Text>
      <PageNumber>10356</PageNumber>
    </MainItem>
  </ItemGroup>
  <ItemGroup>
    <MainItem>
      <Key>
        <KeyDitto>___ ___ ___ ___ ___</KeyDitto>
      </Key>
      <Title>Lt.</Title>
      <Forenames>S. A.</Forenames>
      <Text>(rel. commn., and retains rank of Lt.)</Text>
      <PageNumber>9237</PageNumber>
    </MainItem>
  </ItemGroup>
  <ItemGroup>
    <MainItem>
      <Key>
        <KeyDitto>___ ___ ___ ___</KeyDitto>
      </Key>
      <Title>Lt.</Title>
      <Forenames>T.</Forenames>
      <Text>(rel. commn., and retains rank of Lt.)</Text>
      <PageNumber>10462</PageNumber>
    </MainItem>
  </ItemGroup>
  <ItemGroup>
    <MainItem>
      <Key>Bearden</Key>
      <Title>Lt.</Title>
      <Forenames>P. F.</Forenames>
      <Text>(rel. commn., and retains rank of Lt.)</Text>
      <PageNumber>9775</PageNumber>
    </MainItem>
  </ItemGroup>
  <ItemGroup>
    <MainItem>
      <Key>Bearne</Key>
      <Text>Capt., A. A. (having attained age limit, is retired, and retains rank of Capt.)</Text>
      <PageNumber>8615</PageNumber>
    </MainItem>
  </ItemGroup>
  <ItemGroup>
    <MainItem>
      <Key>Bearsby</Key>
      <Title>Lt.</Title>
      <Forenames>A. F.</Forenames>
      <Text>(trd. to T.A. Res., Gen. List, R.E., from T. Res.)</Text>
      <PageNumber>8440</PageNumber>
    </MainItem>
  </ItemGroup>
  <ItemGroup>
    <MainItem>
      <Key>Beasley</Key>
      <Title>Lt.</Title>
      <Forenames>R. N.</Forenames>
      <Text>(rel. commn., and retains rank of Lt.)</Text>
      <PageNumber>10458</PageNumber>
    </MainItem>
  </ItemGroup>
  <ItemGroup>
    <MainItem>
      <Key>
        <KeyDitto>___ ___ ___ ___ ___ ___</KeyDitto>
      </Key>
      <Title>Maj.</Title>
      <Forenames>T. C. P.</Forenames>
      <Text>(rel. commn., and retains rank of Maj., with permission to wear prescribed uniform)</Text>
      <PageNumber>10575</PageNumber>
    </MainItem>
  </ItemGroup>
  <ItemGroup>
    <MainItem>
      <Key>Beath</Key>
      <Title>Lt.</Title>
      <Forenames>G. C.</Forenames>
      <Text>(rel. commn., and retains rank of Lt.)</Text>
      <PageNumber>10445</PageNumber>
    </MainItem>
  </ItemGroup>
  <ItemGroup>
    <MainItem>
      <Key>Beatie</Key>
      <Text>2nd Lt. W. A. (rel. commn.. and retains rank of 2nd Lt.)</Text>
      <PageNumber>10477</PageNumber>
    </MainItem>
  </ItemGroup>
  <ItemGroup>
    <MainItem>
      <Key>Beattie</Key>
      <Text>Capt. (Bt. Maj.) F. (rel. commn., and retains rank)</Text>
      <PageNumber>10478</PageNumber>
    </MainItem>
  </ItemGroup>
  <ItemGroup>
    <MainItem>
      <Key>
        <KeyDitto>___ ___ ___ ___ ___ ___</KeyDitto>
      </Key>
      <Title>Lt.</Title>
      <Forenames>V. H.</Forenames>
      <Text>(rel. commn., and granted rank of Capt.)</Text>
      <PageNumber>9140</PageNumber>
    </MainItem>
  </ItemGroup>
  <ItemGroup>
    <MainItem>
      <Key>
        <KeyDitto>___ ___ ___</KeyDitto>
      </Key>
      <Text>2nd Lt. W. J. (rel. commn., and retains rank of 2nd Lt.)</Text>
      <PageNumber>10446</PageNumber>
    </MainItem>
  </ItemGroup>
  <ItemGroup>
    <MainItem>
      <Key>Beatty</Key>
      <Title>Lt.</Title>
      <Forenames>U. M.</Forenames>
      <Text>(rel. commn., and granted rank of Capt.)</Text>
      <PageNumber>10115</PageNumber>
    </MainItem>
  </ItemGroup>
  <ItemGroup>
    <MainItem>
      <Key>Beaufoy</Key>
      <Forenames>Hugh Courtenay</Forenames>
      <Text>(2nd Lt.)</Text>
      <PageNumber>9863</PageNumber>
    </MainItem>
  </ItemGroup>
  <ItemGroup>
    <MainItem>
      <Key>
        <KeyDitto>___ ___ ___</KeyDitto>
      </Key>
      <Title>Capt.</Title>
      <Forenames>R. H.</Forenames>
      <Text>, M.C. (rel. commn., and retains rank of Capt.)</Text>
      <PageNumber>9764</PageNumber>
    </MainItem>
  </ItemGroup>
  <ItemGroup>
    <MainItem>
      <Key>Beaumont</Key>
      <Title>Lt.</Title>
      <Forenames>N. E.</Forenames>
      <Text>, M.C. (rel. commn., and retains rank of Lt.)</Text>
      <PageNumber>9024</PageNumber>
    </MainItem>
  </ItemGroup>
  <ItemGroup>
    <MainItem>
      <Key>
        <KeyDitto>___ ___ ___ ___</KeyDitto>
      </Key>
      <Title>Lt.</Title>
      <Forenames>R. H.</Forenames>
      <Text>(rel. eommn., and retains rank of Lt.)</Text>
      <PageNumber>10217</PageNumber>
    </MainItem>
  </ItemGroup>
  <ItemGroup>
    <MainItem>
      <Key>Beausire</Key>
      <Title>Lt.</Title>
      <Forenames>P. J.</Forenames>
      <Text>(rel. commn., and retains rank of Lt.)</Text>
      <PageNumber>10019</PageNumber>
    </MainItem>
  </ItemGroup>
  <ItemGroup>
    <MainItem>
      <Key>
        <KeyDitto>___ ___ ___ ___</KeyDitto>
      </Key>
      <Title>Lt.</Title>
      <Forenames>R. E.</Forenames>
      <Text>(rel. commn., and retains rank of Lt.)</Text>
      <PageNumber>10019</PageNumber>
    </MainItem>
  </ItemGroup>
  <ItemGroup>
    <MainItem>
      <Key>
        <KeyDitto>___ ___ ___</KeyDitto>
      </Key>
      <Text>retains rank of Lt.)</Text>
      <PageNumber>10458</PageNumber>
    </MainItem>
  </ItemGroup>
  <ItemGroup>
    <MainItem>
      <Key>
        <KeyDitto>___ ___ ___</KeyDitto>
      </Key>
      <Text>retains rank of Lt.)</Text>
      <PageNumber>10209</PageNumber>
    </MainItem>
    <SubItem>
      <Text>Lt. R. W. (rel. commn., and retains rank of Lt.)</Text>
      <PageNumber>9142</PageNumber>
    </SubItem>
  </ItemGroup>
  <ItemGroup>
    <MainItem>
      <Key>Beaver</Key>
      <Text>Lt. J. H. (rel. commn., and retains rank of Lt.)</Text>
      <PageNumber>10241</PageNumber>
    </MainItem>
  </ItemGroup>
  <ItemGroup>
    <MainItem>
      <Key>
        <KeyDitto>___ ___</KeyDitto>
      </Key>
      <Forenames>T.A.</Forenames>
      <Text>for absence without leave)</Text>
      <PageNumber>8622</PageNumber>
    </MainItem>
    <SubItem>
      <Text>Lt. J. A. (rel. commn., and retains rank of Lt.)</Text>
      <PageNumber>10113</PageNumber>
    </SubItem>
  </ItemGroup>
  <ItemGroup>
    <MainItem>
      <Key>
        <KeyDitto>___ ___ ___</KeyDitto>
      </Key>
      <Text>retains rank of Capt.)</Text>
      <PageNumber>9866</PageNumber>
    </MainItem>
  </ItemGroup>
  <ItemGroup>
    <MainItem>
      <Key>
        <KeyDitto>___ ___ ___ ___</KeyDitto>
      </Key>
      <Text>retains rank of Lt.)</Text>
      <PageNumber>10348</PageNumber>
    </MainItem>
    <SubItem>
      <Text>Lt.' S. W. (resigns commn., and retains rank of Lt.)</Text>
      <PageNumber>10447</PageNumber>
    </SubItem>
  </ItemGroup>
  <ItemGroup>
    <MainItem>
      <Key>Becke</Key>
      <Title>Lt.</Title>
      <Forenames>H. R.</Forenames>
      <Text>(rel. commn., and retains rank of Lt.)</Text>
      <PageNumber>10700</PageNumber>
    </MainItem>
  </ItemGroup>
  <ItemGroup>
    <MainItem>
      <Key>Beekerleg</Key>
      <Title>Lt.</Title>
      <Forenames>A.</Forenames>
      <Text>, M.C. (rel. commn., and granted rank of Maj.)</Text>
      <PageNumber>9238</PageNumber>
    </MainItem>
  </ItemGroup>
  <ItemGroup>
    <MainItem>
      <Key>
        <KeyDitto>___ ___ ___ ___</KeyDitto>
      </Key>
      <Text>retains rank of Lt.)</Text>
      <PageNumber>10111</PageNumber>
    </MainItem>
  </ItemGroup>
  <ItemGroup>
    <MainItem>
      <Key>
        <KeyDitto>___ ___</KeyDitto>
      </Key>
      <Text>retains rank of Lt.)</Text>
      <PageNumber>10216</PageNumber>
    </MainItem>
  </ItemGroup>
  <ItemGroup>
    <MainItem>
      <Key>
        <KeyDitto>___ ___ '</KeyDitto>
      </Key>
      <Text>retains rank of Lt.) . -</Text>
      <PageNumber>10212</PageNumber>
    </MainItem>
  </ItemGroup>
  <ItemGroup>
    <MainItem>
      <Key>
        <KeyDitto>___ ___ ___</KeyDitto>
      </Key>
      <Text>retains rank of Lt.)</Text>
      <PageNumber>9437</PageNumber>
    </MainItem>
  </ItemGroup>
  <ItemGroup>
    <MainItem>
      <Key>
        <KeyDitto>___ ___</KeyDitto>
      </Key>
      <Text>and retains rank of Lt.)</Text>
      <PageNumber>10459</PageNumber>
    </MainItem>
  </ItemGroup>
  <ItemGroup>
    <MainItem>
      <Key>
        <KeyDitto>___ ___ ___</KeyDitto>
      </Key>
      <Text>and granted rank of Capt.)</Text>
      <PageNumber>10441</PageNumber>
    </MainItem>
    <SubItem>
      <Text>2nd Lt. W. A. (rel. commn., and retains rank of 2nd Lt.)</Text>
      <PageNumber>10459</PageNumber>
    </SubItem>
  </ItemGroup>
  <ItemGroup>
    <MainItem>
      <Key>
        <KeyDitto>___ ___ ___</KeyDitto>
      </Key>
      <Text>r Capt. Hon. W. G. (retired, having attained the age limit, and retains rank of Capt., with permission to wear prescribed uniform)</Text>
      <PageNumber>8064</PageNumber>
    </MainItem>
  </ItemGroup>
  <ItemGroup>
    <MainItem>
      <Key>Beckingham</Key>
      <Title>Lt.</Title>
      <Forenames>C. G.</Forenames>
      <Text>(rel. commn., and granted rank of Capt.)</Text>
      <PageNumber>10358</PageNumber>
    </MainItem>
  </ItemGroup>
  <ItemGroup>
    <MainItem>
      <Key>
        <KeyDitto>___ ___ ___ ___</KeyDitto>
      </Key>
      <Title>Lt.</Title>
      <Forenames>F.</Forenames>
      <Text>(rel. commn., and granted rank of Capt.)</Text>
      <PageNumber>9439</PageNumber>
    </MainItem>
  </ItemGroup>
  <ItemGroup>
    <MainItem>
      <Key>
        <KeyDitto>___ ___ ___ ___</KeyDitto>
      </Key>
      <Title>Lt.</Title>
      <Forenames>H. R. H.</Forenames>
      <Text>(rel. commn., and retains rank of Lt.)</Text>
      <PageNumber>9878</PageNumber>
    </MainItem>
  </ItemGroup>
  <ItemGroup>
    <MainItem>
      <Key>Beckton</Key>
      <Title>Lt.</Title>
      <Forenames>A. J.</Forenames>
      <Text>(rel. commn., and retains rank of Lt.)</Text>
      <PageNumber>8623</PageNumber>
    </MainItem>
  </ItemGroup>
  <ItemGroup>
    <MainItem>
      <Key>Beckwith</Key>
      <Title>Capt.</Title>
      <Forenames>J. F.</Forenames>
      <Text>(rel. commn., and retains rank of Capt.)</Text>
      <PageNumber>10119</PageNumber>
    </MainItem>
  </ItemGroup>
  <ItemGroup>
    <MainItem>
      <Key>Bedborough</Key>
      <Title>Lt.</Title>
      <Forenames>J. H.</Forenames>
      <Text>(rel. commn., and retains rank of Lt.)</Text>
      <PageNumber>8820</PageNumber>
    </MainItem>
  </ItemGroup>
  <ItemGroup>
    <MainItem>
      <Key>Beddie</Key>
      <Title>Lt.</Title>
      <Forenames>W. D.</Forenames>
      <Text>(rel. commn., and retains rank of Lt.)</Text>
      <PageNumber>10445</PageNumber>
    </MainItem>
  </ItemGroup>
  <ItemGroup>
    <MainItem>
      <Key>Beddow</Key>
      <Title>Lt.</Title>
      <Forenames>W. E.</Forenames>
      <Text>(rel. commn., and retains rank of Lt.)</Text>
      <PageNumber>10007</PageNumber>
    </MainItem>
  </ItemGroup>
  <ItemGroup>
    <MainItem>
      <Key>Bedelle</Key>
      <Title>Lt.</Title>
      <Forenames>A. J</Forenames>
      <Text>^. (rel. commn., and retains rank of Lt.)</Text>
      <PageNumber>8813</PageNumber>
    </MainItem>
  </ItemGroup>
  <ItemGroup>
    <MainItem>
      <Key>Bedford</Key>
      <Title>Lt.</Title>
      <Forenames>A. B.</Forenames>
      <Text>(rel. commn., and retains rank of Lt.)</Text>
      <PageNumber>10111</PageNumber>
    </MainItem>
  </ItemGroup>
  <ItemGroup>
    <MainItem>
      <Key>Bedingfield</Key>
      <Title>Gapt.</Title>
      <Forenames>R. W.</Forenames>
      <Text>(rel. commn., and retains rank of Capt.)</Text>
      <PageNumber>10575</PageNumber>
    </MainItem>
  </ItemGroup>
  <ItemGroup>
    <MainItem>
      <Key>Bednall</Key>
      <Title>Lt.</Title>
      <Forenames>H. J.</Forenames>
      <Text>(rel. commn., and retains rank of Lt.)</Text>
      <PageNumber>10458</PageNumber>
    </MainItem>
  </ItemGroup>
  <ItemGroup>
    <MainItem>
      <Key>Bedwell</Key>
      <Title>Lt.</Title>
      <Forenames>J. R.</Forenames>
      <Text>, M.C. (rel. commn., and granted rank of Maj.)</Text>
      <PageNumber>9014</PageNumber>
    </MainItem>
  </ItemGroup>
  <ItemGroup>
    <MainItem>
      <Key>Bedworth</Key>
      <Title>Capt.</Title>
      <Forenames>A. C.</Forenames>
      <Text>(rel. commn., and retains rank of Capt.)</Text>
      <PageNumber>9132</PageNumber>
    </MainItem>
  </ItemGroup>
  <ItemGroup>
    <MainItem>
      <Key>Bee</Key>
      <Title>Maj.</Title>
      <Forenames>A. R.</Forenames>
      <Text>, T.D. (rel. commn., and retains rank of Maj.)</Text>
      <PageNumber>9882</PageNumber>
    </MainItem>
  </ItemGroup>
  <ItemGroup>
    <MainItem>
      <Key>
        <KeyDitto>___ ___</KeyDitto>
      </Key>
      <Title>Maj.</Title>
      <Forenames>F. B. W.</Forenames>
      <Text>(Capt., 53rd (Lond.) Med. Bde., R.G.A., from Dorset R.G.A.)</Text>
      <PageNumber>10447</PageNumber>
    </MainItem>
  </ItemGroup>
  <ItemGroup>
    <MainItem>
      <Key>Beeby</Key>
      <Title>Capt.</Title>
      <Forenames>H. D.</Forenames>
      <Text>(rel. oommn., and retains rank of Capt.)</Text>
      <PageNumber>10009</PageNumber>
    </MainItem>
  </ItemGroup>
  <ItemGroup>
    <MainItem>
      <Key>Beech</Key>
      <Title>Lt.</Title>
      <Forenames>F. C.</Forenames>
      <Text>(rel. commn., and retains rank of Lt.)</Text>
      <PageNumber>10214</PageNumber>
    </MainItem>
  </ItemGroup>
  <ItemGroup>
    <MainItem>
      <Key>
        <KeyDitto>___ ___</KeyDitto>
      </Key>
      <Title>Lt.</Title>
      <Forenames>H.</Forenames>
      <Text>(rel. commn., and retains rank of Lt.)</Text>
      <PageNumber>10116</PageNumber>
    </MainItem>
  </ItemGroup>
  <ItemGroup>
    <MainItem>
      <Key>
        <KeyDitto>___ ___ ___</KeyDitto>
      </Key>
      <Title>Lt.</Title>
      <Forenames>R. F.</Forenames>
      <Text>, M.C. (rel. commn., and retains rank of Lt.)</Text>
      <PageNumber>10347</PageNumber>
    </MainItem>
  </ItemGroup>
</Index>

