<?xml version="1.0" encoding="UTF-8"?>
<Index xmlns="http://www.tso.co.uk/assets/namespace/gazetteindex" editionCode="L" page="035" pageID="https://www.thegazette.co.uk/id/London/index/year/1927/volume/3/page/035" pagePDF="https://www.thegazette.co.uk/London/index/year/1927/volume/3/page/035" pageRDF="https://www.thegazette.co.uk/London/index/year/1927/volume/3/page/035?view=linked-data" type="index" volume="3" year="1927">
  <ItemGroup>
    <MainItem>
      <Key>Imrie</Key>
      <Forenames>D. A.</Forenames>
      <PageNumber>5177</PageNumber>
    </MainItem>
  </ItemGroup>
  <ItemGroup>
    <MainItem>
      <Key>Jaquin</Key>
      <Forenames>E. N .</Forenames>
      <PageNumber>5733</PageNumber>
    </MainItem>
  </ItemGroup>
  <ItemGroup>
    <MainItem>
      <Key>Johnson</Key>
      <Forenames>C. J.</Forenames>
      <PageNumber>4717</PageNumber>
    </MainItem>
  </ItemGroup>
  <ItemGroup>
    <MainItem>
      <Key>Kendall</Key>
      <Forenames>A. W .</Forenames>
      <PageNumber>5393</PageNumber>
    </MainItem>
  </ItemGroup>
  <ItemGroup>
    <MainItem>
      <Key>McOombe</Key>
      <Forenames>G. A. K.</Forenames>
      <PageNumber>5333</PageNumber>
    </MainItem>
  </ItemGroup>
  <ItemGroup>
    <MainItem>
      <Key>MoConnell</Key>
      <Forenames>R. M. T.</Forenames>
      <PageNumber>5605</PageNumber>
    </MainItem>
  </ItemGroup>
  <ItemGroup>
    <MainItem>
      <Key>McCormiok</Key>
      <Forenames>J.</Forenames>
      <PageNumber>5260</PageNumber>
    </MainItem>
  </ItemGroup>
  <ItemGroup>
    <MainItem>
      <Key>McKechnie</Key>
      <Forenames>D. M.</Forenames>
      <PageNumber>4645</PageNumber>
    </MainItem>
  </ItemGroup>
  <ItemGroup>
    <MainItem>
      <Key>McLaughlin</Key>
      <Forenames>F. A.</Forenames>
      <PageNumber>6186</PageNumber>
    </MainItem>
  </ItemGroup>
  <ItemGroup>
    <MainItem>
      <Key>Mardon</Key>
      <Forenames>P. R .</Forenames>
      <PageNumber>4997</PageNumber>
    </MainItem>
  </ItemGroup>
  <ItemGroup>
    <MainItem>
      <Key>Monk</Key>
      <Forenames>G. P .</Forenames>
      <PageNumber>5539</PageNumber>
    </MainItem>
  </ItemGroup>
  <ItemGroup>
    <MainItem>
      <Key>Nalson</Key>
      <Forenames>L. D .</Forenames>
      <PageNumber>5260</PageNumber>
    </MainItem>
  </ItemGroup>
  <ItemGroup>
    <MainItem>
      <Key>Nicholson</Key>
      <Forenames>B. D.</Forenames>
      <PageNumber>5106</PageNumber>
    </MainItem>
  </ItemGroup>
  <ItemGroup>
    <MainItem>
      <Key>Parry-Price</Key>
      <Forenames>H.</Forenames>
      <PageNumber>5539</PageNumber>
    </MainItem>
  </ItemGroup>
  <ItemGroup>
    <MainItem>
      <Key>Robertson</Key>
      <Text>' J. McK</Text>
      <PageNumber>4235</PageNumber>
    </MainItem>
  </ItemGroup>
  <ItemGroup>
    <MainItem>
      <Key>Rogers</Key>
      <Forenames>L. C.</Forenames>
      <PageNumber>5670</PageNumber>
    </MainItem>
  </ItemGroup>
  <ItemGroup>
    <MainItem>
      <Key>Searle</Key>
      <Forenames>S.</Forenames>
      <PageNumber>4996</PageNumber>
    </MainItem>
  </ItemGroup>
  <ItemGroup>
    <MainItem>
      <Key>Smail</Key>
      <Forenames>W. M .</Forenames>
      <PageNumber>4235</PageNumber>
    </MainItem>
  </ItemGroup>
  <ItemGroup>
    <MainItem>
      <Key>Stabler</Key>
      <Forenames>F. E .</Forenames>
      <PageNumber>5259</PageNumber>
    </MainItem>
  </ItemGroup>
  <ItemGroup>
    <MainItem>
      <Key>Thomas</Key>
      <Forenames>A. R.</Forenames>
      <PageNumber>5670</PageNumber>
    </MainItem>
  </ItemGroup>
  <ItemGroup>
    <MainItem>
      <Key>
        <KeyDitto>___</KeyDitto>
      </Key>
      <Forenames>A. T. G.</Forenames>
      <PageNumber>5394</PageNumber>
    </MainItem>
  </ItemGroup>
  <ItemGroup>
    <MainItem>
      <Key>Todd</Key>
      <Forenames>J. C .</Forenames>
      <PageNumber>5539</PageNumber>
    </MainItem>
  </ItemGroup>
  <SubSectionTitle>Royal Naval 'Volunteer Reserve Officers</SubSectionTitle>
  <SubSectionTitle>Decoration</SubSectionTitle>
  <ItemGroup>
    <MainItem>
      <Key>Reade</Key>
      <Forenames>A. G. L.</Forenames>
      <PageNumber>5605</PageNumber>
    </MainItem>
  </ItemGroup>
  <ItemGroup>
    <MainItem>
      <Key>Adkins</Key>
      <Forenames>H. J</Forenames>
      <PageNumber>4240</PageNumber>
    </MainItem>
  </ItemGroup>
  <ItemGroup>
    <MainItem>
      <Key>Airey</Key>
      <Forenames>J. L</Forenames>
      <PageNumber>4240</PageNumber>
    </MainItem>
  </ItemGroup>
  <ItemGroup>
    <MainItem>
      <Key>Alexander</Key>
      <Forenames>J. R. W</Forenames>
      <PageNumber>4841</PageNumber>
    </MainItem>
  </ItemGroup>
  <ItemGroup>
    <MainItem>
      <Key>Allen</Key>
      <Forenames>A. W. L. C</Forenames>
      <PageNumber>4328</PageNumber>
    </MainItem>
  </ItemGroup>
  <ItemGroup>
    <MainItem>
      <Key>
        <KeyDitto>___ ___</KeyDitto>
      </Key>
      <Forenames>F. T.</Forenames>
      <PageNumber>5336</PageNumber>
    </MainItem>
  </ItemGroup>
  <ItemGroup>
    <MainItem>
      <Key>
        <KeyDitto>___ ___</KeyDitto>
      </Key>
      <Forenames>J. B.</Forenames>
      <PageNumber>6003</PageNumber>
    </MainItem>
  </ItemGroup>
  <ItemGroup>
    <MainItem>
      <Key>
        <KeyDitto>___ ___</KeyDitto>
      </Key>
      <Forenames>M. D</Forenames>
      <PageNumber>5805</PageNumber>
    </MainItem>
  </ItemGroup>
  <ItemGroup>
    <MainItem>
      <Key>
        <KeyDitto>___ ___</KeyDitto>
      </Key>
      <Forenames>R. E. H</Forenames>
      <PageNumber>4240</PageNumber>
    </MainItem>
  </ItemGroup>
  <ItemGroup>
    <MainItem>
      <Key>Alliott</Key>
      <Forenames>E. H</Forenames>
      <PageNumber>4649</PageNumber>
    </MainItem>
  </ItemGroup>
  <ItemGroup>
    <MainItem>
      <Key>Anderson</Key>
      <Forenames>C. A.</Forenames>
      <PageNumber>5608</PageNumber>
    </MainItem>
  </ItemGroup>
  <ItemGroup>
    <MainItem>
      <Key>Andrews</Key>
      <Forenames>W. A.</Forenames>
      <PageNumber>5000</PageNumber>
    </MainItem>
  </ItemGroup>
  <ItemGroup>
    <MainItem>
      <Key>Anness</Key>
      <Forenames>L. H</Forenames>
      <PageNumber>6002</PageNumber>
    </MainItem>
  </ItemGroup>
  <ItemGroup>
    <MainItem>
      <Key>Anstice</Key>
      <Forenames>E. W</Forenames>
      <PageNumber>4240</PageNumber>
    </MainItem>
  </ItemGroup>
  <ItemGroup>
    <MainItem>
      <Key>Appleton</Key>
      <Forenames>C. H.</Forenames>
      <PageNumber>6127</PageNumber>
    </MainItem>
  </ItemGroup>
  <ItemGroup>
    <MainItem>
      <Key>Armitage</Key>
      <Forenames>E. H.</Forenames>
      <PageNumber>6003</PageNumber>
    </MainItem>
  </ItemGroup>
  <ItemGroup>
    <MainItem>
      <Key>Ash</Key>
      <Forenames>L. S.</Forenames>
      <PageNumber>4841</PageNumber>
    </MainItem>
  </ItemGroup>
  <ItemGroup>
    <MainItem>
      <Key>Ashton</Key>
      <Forenames>B. H .</Forenames>
      <PageNumber>4841</PageNumber>
    </MainItem>
  </ItemGroup>
  <ItemGroup>
    <MainItem>
      <Key>
        <KeyDitto>___</KeyDitto>
      </Key>
      <Forenames>C. F.</Forenames>
      <PageNumber>4649</PageNumber>
    </MainItem>
  </ItemGroup>
  <ItemGroup>
    <MainItem>
      <Key>Ashton-Jinks</Key>
      <Forenames>C. P</Forenames>
      <PageNumber>5608</PageNumber>
    </MainItem>
  </ItemGroup>
  <ItemGroup>
    <MainItem>
      <Key>Atkins</Key>
      <Forenames>W. R. G.</Forenames>
      <PageNumber>4841</PageNumber>
    </MainItem>
  </ItemGroup>
  <ItemGroup>
    <MainItem>
      <Key>Atkinson</Key>
      <Forenames>C. J. N.</Forenames>
      <PageNumber>4240</PageNumber>
    </MainItem>
  </ItemGroup>
  <ItemGroup>
    <MainItem>
      <Key>
        <KeyDitto>___ ___</KeyDitto>
      </Key>
      <Forenames>P. G. J.</Forenames>
      <PageNumber>4840</PageNumber>
    </MainItem>
  </ItemGroup>
  <ItemGroup>
    <MainItem>
      <Key>Ayling</Key>
      <Forenames>H. O. K.</Forenames>
      <Text>' ... .;</Text>
      <PageNumber>6003</PageNumber>
    </MainItem>
  </ItemGroup>
  <ItemGroup>
    <MainItem>
      <Key>Bailey</Key>
      <Forenames>F. H.</Forenames>
      <PageNumber>5872</PageNumber>
    </MainItem>
  </ItemGroup>
  <ItemGroup>
    <MainItem>
      <Key>Bain</Key>
      <Forenames>R. E</Forenames>
      <PageNumber>4497</PageNumber>
    </MainItem>
  </ItemGroup>
  <ItemGroup>
    <MainItem>
      <Key>Baines</Key>
      <Forenames>J.</Forenames>
      <PageNumber>6128</PageNumber>
    </MainItem>
  </ItemGroup>
  <ItemGroup>
    <MainItem>
      <Key>Baker</Key>
      <Forenames>O. H</Forenames>
      <PageNumber>5181</PageNumber>
    </MainItem>
  </ItemGroup>
  <ItemGroup>
    <MainItem>
      <Key>
        <KeyDitto>___ ___ ___</KeyDitto>
      </Key>
      <Forenames>P. D.</Forenames>
      <PageNumber>4497</PageNumber>
    </MainItem>
  </ItemGroup>
  <ItemGroup>
    <MainItem>
      <Key>Ballantyne</Key>
      <Forenames>G. A.</Forenames>
      <PageNumber>4841</PageNumber>
      <PageNumber>5805</PageNumber>
    </MainItem>
  </ItemGroup>
  <ItemGroup>
    <MainItem>
      <Key>Barclay</Key>
      <Forenames>M. B</Forenames>
      <PageNumber>5181</PageNumber>
    </MainItem>
  </ItemGroup>
  <ItemGroup>
    <MainItem>
      <Key>Barker</Key>
      <Text>CP</Text>
      <PageNumber>4648</PageNumber>
    </MainItem>
  </ItemGroup>
  <ItemGroup>
    <MainItem>
      <Key>Barling</Key>
      <Forenames>P. D</Forenames>
      <PageNumber>6128</PageNumber>
    </MainItem>
  </ItemGroup>
  <ItemGroup>
    <MainItem>
      <Key>Barlow</Key>
      <Text>, H. D</Text>
      <PageNumber>5335</PageNumber>
    </MainItem>
  </ItemGroup>
  <ItemGroup>
    <MainItem>
      <Key>Barnes</Key>
      <Forenames>E. D</Forenames>
      <PageNumber>4240</PageNumber>
    </MainItem>
  </ItemGroup>
  <ItemGroup>
    <MainItem>
      <Key>Barnett</Key>
      <Forenames>D. H. F</Forenames>
      <PageNumber>5678</PageNumber>
    </MainItem>
  </ItemGroup>
  <ItemGroup>
    <MainItem>
      <Key>Barrett</Key>
      <Forenames>R. E</Forenames>
      <PageNumber>4240</PageNumber>
    </MainItem>
  </ItemGroup>
  <ItemGroup>
    <MainItem>
      <Key>Barron</Key>
      <Text>D</Text>
      <PageNumber>4649</PageNumber>
    </MainItem>
  </ItemGroup>
  <ItemGroup>
    <MainItem>
      <Key>Barrow</Key>
      <Forenames>H. A. J.</Forenames>
      <Text>de S</Text>
      <PageNumber>5335</PageNumber>
    </MainItem>
  </ItemGroup>
  <ItemGroup>
    <MainItem>
      <Key>Barry</Key>
      <Forenames>A. S</Forenames>
      <PageNumber>4648</PageNumber>
    </MainItem>
  </ItemGroup>
  <ItemGroup>
    <MainItem>
      <Key>Bartholomew</Key>
      <Forenames>G.</Forenames>
      <PageNumber>6128</PageNumber>
    </MainItem>
  </ItemGroup>
  <ItemGroup>
    <MainItem>
      <Key>Barton</Key>
      <Forenames>B. W</Forenames>
      <PageNumber>6128</PageNumber>
    </MainItem>
  </ItemGroup>
  <ItemGroup>
    <MainItem>
      <Key>Batchelor</Key>
      <Text>E</Text>
      <PageNumber>5678</PageNumber>
    </MainItem>
  </ItemGroup>
  <ItemGroup>
    <MainItem>
      <Key>Bateman</Key>
      <Forenames>E. S.</Forenames>
      <PageNumber>4648</PageNumber>
    </MainItem>
  </ItemGroup>
  <ItemGroup>
    <MainItem>
      <Key>Bates</Key>
      <Forenames>E. M</Forenames>
      <PageNumber>5181</PageNumber>
    </MainItem>
  </ItemGroup>
  <ItemGroup>
    <MainItem>
      <Key>Bazell</Key>
      <Forenames>C. C</Forenames>
      <PageNumber>4240</PageNumber>
    </MainItem>
  </ItemGroup>
  <ItemGroup>
    <MainItem>
      <Key>Seesley</Key>
      <Forenames>I. B</Forenames>
      <PageNumber>4840</PageNumber>
    </MainItem>
  </ItemGroup>
  <ItemGroup>
    <MainItem>
      <Key>Beilbv</Key>
      <Forenames>A. E</Forenames>
      <PageNumber>4240</PageNumber>
    </MainItem>
  </ItemGroup>
  <ItemGroup>
    <MainItem>
      <Key>Benham</Key>
      <Forenames>R.</Forenames>
      <PageNumber>5000</PageNumber>
    </MainItem>
  </ItemGroup>
  <ItemGroup>
    <MainItem>
      <Key>Bennett</Key>
      <Forenames>A. D.</Forenames>
      <PageNumber>6127</PageNumber>
    </MainItem>
  </ItemGroup>
  <ItemGroup>
    <MainItem>
      <Key>
        <KeyDitto>___ ___</KeyDitto>
      </Key>
      <Forenames>L. V.</Forenames>
      <PageNumber>6127</PageNumber>
    </MainItem>
  </ItemGroup>
  <ItemGroup>
    <MainItem>
      <Key>
        <KeyDitto>___ ___</KeyDitto>
      </Key>
      <Forenames>V. G. A</Forenames>
      <PageNumber>4240</PageNumber>
    </MainItem>
  </ItemGroup>
  <ItemGroup>
    <MainItem>
      <Key>Benstead</Key>
      <Forenames>F.E. C</Forenames>
      <PageNumber>5804</PageNumber>
    </MainItem>
  </ItemGroup>
  <ItemGroup>
    <MainItem>
      <Key>Berkeley</Key>
      <Forenames>A. P. F. M.</Forenames>
      <PageNumber>5608</PageNumber>
    </MainItem>
  </ItemGroup>
  <ItemGroup>
    <MainItem>
      <Key>Berry</Key>
      <Forenames>A. S</Forenames>
      <PageNumber>4240</PageNumber>
    </MainItem>
  </ItemGroup>
  <ItemGroup>
    <MainItem>
      <Key>Bett</Key>
      <Text>A. P</Text>
      <PageNumber>4497</PageNumber>
    </MainItem>
  </ItemGroup>
  <ItemGroup>
    <MainItem>
      <Key>Bettington</Key>
      <Forenames>A. V</Forenames>
      <PageNumber>4239</PageNumber>
    </MainItem>
  </ItemGroup>
  <ItemGroup>
    <MainItem>
      <Key>Bevan</Key>
      <Forenames>C. M</Forenames>
      <PageNumber>4240</PageNumber>
    </MainItem>
  </ItemGroup>
  <ItemGroup>
    <MainItem>
      <Key>Bingham</Key>
      <Forenames>S .</Forenames>
      <PageNumber>4240</PageNumber>
    </MainItem>
  </ItemGroup>
  <ItemGroup>
    <MainItem>
      <Key>Bircham</Key>
      <Forenames>M. G.</Forenames>
      <PageNumber>4648</PageNumber>
    </MainItem>
  </ItemGroup>
  <ItemGroup>
    <MainItem>
      <Key>Birks</Key>
      <Forenames>N. P .</Forenames>
      <PageNumber>4649</PageNumber>
    </MainItem>
  </ItemGroup>
  <ItemGroup>
    <MainItem>
      <Key>Bolt</Key>
      <Forenames>J. E.</Forenames>
      <PageNumber>4649</PageNumber>
    </MainItem>
  </ItemGroup>
  <ItemGroup>
    <MainItem>
      <Key>Booth</Key>
      <Forenames>P.</Forenames>
      <PageNumber>5336</PageNumber>
    </MainItem>
  </ItemGroup>
  <ItemGroup>
    <MainItem>
      <Key>Boothman</Key>
      <Forenames>J. N.</Forenames>
      <PageNumber>4240</PageNumber>
    </MainItem>
  </ItemGroup>
  <ItemGroup>
    <MainItem>
      <Key>Borthwick-Clarke</Key>
      <Forenames>E. S.</Forenames>
      <PageNumber>5335</PageNumber>
    </MainItem>
  </ItemGroup>
  <ItemGroup>
    <MainItem>
      <Key>Bourne</Key>
      <Forenames>F. W .</Forenames>
      <PageNumber>4841</PageNumber>
    </MainItem>
  </ItemGroup>
  <ItemGroup>
    <MainItem>
      <Key>Bowler</Key>
      <Forenames>T. G .</Forenames>
      <PageNumber>5608</PageNumber>
    </MainItem>
  </ItemGroup>
  <ItemGroup>
    <MainItem>
      <Key>Bowles</Key>
      <Forenames>J. E. W.</Forenames>
      <PageNumber>4840</PageNumber>
    </MainItem>
  </ItemGroup>
  <ItemGroup>
    <MainItem>
      <Key>Box</Key>
      <Forenames>H .</Forenames>
      <PageNumber>5608</PageNumber>
    </MainItem>
  </ItemGroup>
  <ItemGroup>
    <MainItem>
      <Key>Boyce</Key>
      <Forenames>C. D. C.</Forenames>
      <PageNumber>4841</PageNumber>
    </MainItem>
  </ItemGroup>
  <ItemGroup>
    <MainItem>
      <Key>Brackley</Key>
      <Forenames>H. G.</Forenames>
      <PageNumber>4240</PageNumber>
    </MainItem>
  </ItemGroup>
  <ItemGroup>
    <MainItem>
      <Key>Bradbury</Key>
      <Forenames>J. Bradford</Forenames>
      <Text>, W. W</Text>
      <PageNumber>4238</PageNumber>
      <PageNumber>4649</PageNumber>
    </MainItem>
  </ItemGroup>
  <ItemGroup>
    <MainItem>
      <Key>Brett</Key>
      <Forenames>J.</Forenames>
      <PageNumber>5335</PageNumber>
    </MainItem>
  </ItemGroup>
  <ItemGroup>
    <MainItem>
      <Key>Brewster</Key>
      <Forenames>K. W.</Forenames>
      <PageNumber>4649</PageNumber>
    </MainItem>
  </ItemGroup>
  <ItemGroup>
    <MainItem>
      <Key>Briddon</Key>
      <Forenames>A. J.</Forenames>
      <PageNumber>4240</PageNumber>
    </MainItem>
  </ItemGroup>
  <ItemGroup>
    <MainItem>
      <Key>Bridges</Key>
      <Forenames>F. E.</Forenames>
      <PageNumber>5001</PageNumber>
    </MainItem>
  </ItemGroup>
  <ItemGroup>
    <MainItem>
      <Key>Briggs</Key>
      <Forenames>C. F .</Forenames>
      <PageNumber>4649</PageNumber>
    </MainItem>
  </ItemGroup>
  <ItemGroup>
    <MainItem>
      <Key>Brinton</Key>
      <Forenames>G. L.</Forenames>
      <PageNumber>5335</PageNumber>
    </MainItem>
  </ItemGroup>
  <ItemGroup>
    <MainItem>
      <Key>Brodie</Key>
      <Forenames>I. E .</Forenames>
      <PageNumber>4240</PageNumber>
    </MainItem>
  </ItemGroup>
  <ItemGroup>
    <MainItem>
      <Key>Brooks</Key>
      <Forenames>G.</Forenames>
      <PageNumber>4240</PageNumber>
    </MainItem>
  </ItemGroup>
  <ItemGroup>
    <MainItem>
      <Key>Brown</Key>
      <Forenames>B. E .</Forenames>
      <PageNumber>6127</PageNumber>
    </MainItem>
  </ItemGroup>
  <ItemGroup>
    <MainItem>
      <Key>
        <KeyDitto>___ ___ ___</KeyDitto>
      </Key>
      <Forenames>H. J .</Forenames>
      <PageNumber>4240</PageNumber>
    </MainItem>
  </ItemGroup>
  <ItemGroup>
    <MainItem>
      <Key>
        <KeyDitto>___ ___</KeyDitto>
      </Key>
      <Forenames>H. M. K .</Forenames>
      <PageNumber>4240</PageNumber>
    </MainItem>
  </ItemGroup>
  <ItemGroup>
    <MainItem>
      <Key>
        <KeyDitto>___ ___</KeyDitto>
      </Key>
      <Forenames>T. W. S .</Forenames>
      <PageNumber>4240</PageNumber>
    </MainItem>
  </ItemGroup>
  <ItemGroup>
    <MainItem>
      <Key>Browne</Key>
      <Forenames>G. R. S.</Forenames>
      <PageNumber>5336</PageNumber>
    </MainItem>
  </ItemGroup>
  <ItemGroup>
    <MainItem>
      <Key>Browning</Key>
      <Forenames>N. M.</Forenames>
      <PageNumber>4841</PageNumber>
    </MainItem>
  </ItemGroup>
  <ItemGroup>
    <MainItem>
      <Key>Bruce</Key>
      <Forenames>R. S .</Forenames>
      <PageNumber>4240</PageNumber>
    </MainItem>
  </ItemGroup>
  <ItemGroup>
    <MainItem>
      <Key>
        <KeyDitto>___ ___</KeyDitto>
      </Key>
      <Forenames>T. B.</Forenames>
      <PageNumber>4240</PageNumber>
    </MainItem>
  </ItemGroup>
  <ItemGroup>
    <MainItem>
      <Key>Buchany</Key>
      <Forenames>E. A</Forenames>
      <PageNumber>5336</PageNumber>
      <PageNumber>6128</PageNumber>
    </MainItem>
  </ItemGroup>
  <ItemGroup>
    <MainItem>
      <Key>Buckley</Key>
      <Forenames>J. B .</Forenames>
      <PageNumber>5335</PageNumber>
    </MainItem>
  </ItemGroup>
  <ItemGroup>
    <MainItem>
      <Key>Bullen</Key>
      <Forenames>E. S .</Forenames>
      <PageNumber>4240</PageNumber>
    </MainItem>
  </ItemGroup>
  <ItemGroup>
    <MainItem>
      <Key>Bullmore</Key>
      <Forenames>F. T. K.</Forenames>
      <PageNumber>4840</PageNumber>
    </MainItem>
  </ItemGroup>
  <ItemGroup>
    <MainItem>
      <Key>Burney-Cumming</Key>
      <Forenames>J. C.</Forenames>
      <PageNumber>6128</PageNumber>
    </MainItem>
  </ItemGroup>
  <ItemGroup>
    <MainItem>
      <Key>Burt</Key>
      <Forenames>H. S. R .</Forenames>
      <PageNumber>4497</PageNumber>
    </MainItem>
  </ItemGroup>
  <ItemGroup>
    <MainItem>
      <Key>Burton</Key>
      <Text>E. A</Text>
      <PageNumber>5872</PageNumber>
    </MainItem>
  </ItemGroup>
  <ItemGroup>
    <MainItem>
      <Key>
        <KeyDitto>___ ___ ___</KeyDitto>
      </Key>
      <Forenames>H. E. N .</Forenames>
      <PageNumber>5608</PageNumber>
    </MainItem>
  </ItemGroup>
  <ItemGroup>
    <MainItem>
      <Key>Butler</Key>
      <Forenames>W. D</Forenames>
      <Text>Caddy, H. H</Text>
      <PageNumber>5335</PageNumber>
    </MainItem>
  </ItemGroup>
  <ItemGroup>
    <MainItem>
      <Key>Calvev</Key>
      <Forenames>H. C</Forenames>
      <Text>Campbell, G. E</Text>
      <PageNumber>6003</PageNumber>
    </MainItem>
  </ItemGroup>
  <ItemGroup>
    <MainItem>
      <Key>Candy</Key>
      <Forenames>M. G .</Forenames>
      <PageNumber>5678</PageNumber>
    </MainItem>
  </ItemGroup>
  <ItemGroup>
    <MainItem>
      <Key>Cardwell</Key>
      <Forenames>H. E .</Forenames>
      <PageNumber>4649</PageNumber>
    </MainItem>
  </ItemGroup>
  <ItemGroup>
    <MainItem>
      <Key>Carter</Key>
      <Forenames>B. P. B.</Forenames>
      <PageNumber>4841</PageNumber>
    </MainItem>
  </ItemGroup>
  <ItemGroup>
    <MainItem>
      <Key>
        <KeyDitto>___ ___ ___ ___</KeyDitto>
      </Key>
      <Forenames>G. P. H.</Forenames>
      <PageNumber>4240</PageNumber>
    </MainItem>
  </ItemGroup>
  <ItemGroup>
    <MainItem>
      <Key>Chalmers</Key>
      <Forenames>C. W. S.</Forenames>
      <PageNumber>6003</PageNumber>
    </MainItem>
  </ItemGroup>
  <ItemGroup>
    <MainItem>
      <Key>Charnock</Key>
      <Forenames>H. W.</Forenames>
      <PageNumber>4497</PageNumber>
    </MainItem>
  </ItemGroup>
  <ItemGroup>
    <MainItem>
      <Key>Cheshire</Key>
      <Forenames>W. G .</Forenames>
      <PageNumber>4841</PageNumber>
    </MainItem>
  </ItemGroup>
  <ItemGroup>
    <MainItem>
      <Key>Chipper</Key>
      <Forenames>A. A. B.</Forenames>
      <PageNumber>4240</PageNumber>
    </MainItem>
  </ItemGroup>
  <ItemGroup>
    <MainItem>
      <Key>Chisman</Key>
      <Forenames>L.</Forenames>
      <Text>de V</Text>
      <PageNumber>4841</PageNumber>
    </MainItem>
  </ItemGroup>
  <ItemGroup>
    <MainItem>
      <Key>Christie</Key>
      <Forenames>M. G .</Forenames>
      <PageNumber>5678</PageNumber>
    </MainItem>
  </ItemGroup>
  <ItemGroup>
    <MainItem>
      <Key>Clark</Key>
      <Forenames>D. H. B .</Forenames>
      <PageNumber>6003</PageNumber>
    </MainItem>
  </ItemGroup>
  <ItemGroup>
    <MainItem>
      <Key>
        <KeyDitto>___ ___ .</KeyDitto>
      </Key>
      <Forenames>E. S.</Forenames>
      <PageNumber>4840</PageNumber>
    </MainItem>
  </ItemGroup>
  <ItemGroup>
    <MainItem>
      <Key>
        <KeyDitto>___ ___ ___ ___</KeyDitto>
      </Key>
      <Forenames>R. W. M .</Forenames>
      <PageNumber>5001</PageNumber>
    </MainItem>
  </ItemGroup>
  <ItemGroup>
    <MainItem>
      <Key>Clarke</Key>
      <Forenames>D. F. A .</Forenames>
      <PageNumber>5678</PageNumber>
    </MainItem>
  </ItemGroup>
  <ItemGroup>
    <MainItem>
      <Key>
        <KeyDitto>___ ___ ___ ___</KeyDitto>
      </Key>
      <Forenames>P. S .</Forenames>
      <PageNumber>5335</PageNumber>
    </MainItem>
  </ItemGroup>
  <ItemGroup>
    <MainItem>
      <Key>Clemson</Key>
      <Forenames>A. W.</Forenames>
      <Text>... . '</Text>
      <PageNumber>4240</PageNumber>
    </MainItem>
  </ItemGroup>
  <ItemGroup>
    <MainItem>
      <Key>Cole</Key>
      <Forenames>S. N .</Forenames>
      <PageNumber>5678</PageNumber>
    </MainItem>
  </ItemGroup>
  <ItemGroup>
    <MainItem>
      <Key>Coleman</Key>
      <Forenames>J. A.</Forenames>
      <PageNumber>4240</PageNumber>
    </MainItem>
  </ItemGroup>
  <ItemGroup>
    <MainItem>
      <Key>
        <KeyDitto>___ ___</KeyDitto>
      </Key>
      <Forenames>J. P .</Forenames>
      <PageNumber>5805</PageNumber>
    </MainItem>
  </ItemGroup>
  <ItemGroup>
    <MainItem>
      <Key>Colledge</Key>
      <Forenames>G .</Forenames>
      <PageNumber>4648</PageNumber>
    </MainItem>
  </ItemGroup>
  <ItemGroup>
    <MainItem>
      <Key>Collings</Key>
      <Forenames>R. W. P. Collins</Forenames>
      <Text>, H. B</Text>
      <PageNumber>6128</PageNumber>
    </MainItem>
  </ItemGroup>
  <ItemGroup>
    <MainItem>
      <Key>
        <KeyDitto>___ ___ ___</KeyDitto>
      </Key>
      <Forenames>M. C .</Forenames>
      <PageNumber>6127</PageNumber>
    </MainItem>
  </ItemGroup>
  <ItemGroup>
    <MainItem>
      <Key>Combe</Key>
      <Forenames>A. R.</Forenames>
      <PageNumber>4840</PageNumber>
    </MainItem>
  </ItemGroup>
  <ItemGroup>
    <MainItem>
      <Key>Cooch</Key>
      <Forenames>H.</Forenames>
      <PageNumber>5181</PageNumber>
    </MainItem>
  </ItemGroup>
  <ItemGroup>
    <MainItem>
      <Key>Cook</Key>
      <Forenames>A. F.</Forenames>
      <PageNumber>5872</PageNumber>
    </MainItem>
  </ItemGroup>
  <ItemGroup>
    <MainItem>
      <Key>Cooke</Key>
      <Text>de L</Text>
      <PageNumber>5608</PageNumber>
    </MainItem>
  </ItemGroup>
  <ItemGroup>
    <MainItem>
      <Key>Coope</Key>
      <Forenames>B. R. C.</Forenames>
      <PageNumber>5001</PageNumber>
    </MainItem>
  </ItemGroup>
  <ItemGroup>
    <MainItem>
      <Key>Copley</Key>
      <Forenames>R. J.</Forenames>
      <PageNumber>5001</PageNumber>
    </MainItem>
  </ItemGroup>
  <ItemGroup>
    <MainItem>
      <Key>Corballis</Key>
      <Forenames>E. R</Forenames>
      <Text>, L</Text>
      <PageNumber>4240</PageNumber>
    </MainItem>
  </ItemGroup>
  <ItemGroup>
    <MainItem>
      <Key>Cornewall-Walker</Key>
      <Forenames>T. J. R.</Forenames>
      <PageNumber>5678</PageNumber>
    </MainItem>
  </ItemGroup>
  <ItemGroup>
    <MainItem>
      <Key>Cox</Key>
      <Forenames>B. F .</Forenames>
      <PageNumber>5001</PageNumber>
    </MainItem>
  </ItemGroup>
  <ItemGroup>
    <MainItem>
      <Key>Craig</Key>
      <Forenames>S.</Forenames>
      <Text>McG</Text>
      <PageNumber>5181</PageNumber>
    </MainItem>
  </ItemGroup>
  <ItemGroup>
    <MainItem>
      <Key>Crawford</Key>
      <Forenames>F. B. C. L. B .</Forenames>
      <PageNumber>5336</PageNumber>
    </MainItem>
  </ItemGroup>
  <ItemGroup>
    <MainItem>
      <Key>Crofton</Key>
      <Forenames>R. D .</Forenames>
      <PageNumber>4497</PageNumber>
    </MainItem>
  </ItemGroup>
  <ItemGroup>
    <MainItem>
      <Key>Cross</Key>
      <Forenames>H. J.</Forenames>
      <PageNumber>4840</PageNumber>
    </MainItem>
  </ItemGroup>
  <ItemGroup>
    <MainItem>
      <Key>Crummy</Key>
      <Forenames>B. A. J.</Forenames>
      <PageNumber>4841</PageNumber>
    </MainItem>
  </ItemGroup>
  <ItemGroup>
    <MainItem>
      <Key>Culverwell</Key>
      <Forenames>E. V.</Forenames>
      <PageNumber>5001</PageNumber>
    </MainItem>
  </ItemGroup>
  <ItemGroup>
    <MainItem>
      <Key>Currie</Key>
      <Forenames>L.</Forenames>
      <PageNumber>5872</PageNumber>
    </MainItem>
  </ItemGroup>
  <ItemGroup>
    <MainItem>
      <Key>Dalrymple</Key>
      <Forenames>H. C. E. C. P.</Forenames>
      <PageNumber>6003</PageNumber>
    </MainItem>
  </ItemGroup>
  <ItemGroup>
    <MainItem>
      <Key>Daly</Key>
      <Forenames>G. D .</Forenames>
      <PageNumber>5872</PageNumber>
      <PageNumber>6128</PageNumber>
    </MainItem>
  </ItemGroup>
  <ItemGroup>
    <MainItem>
      <Key>Davidson</Key>
      <Forenames>T. J .</Forenames>
      <PageNumber>4648</PageNumber>
    </MainItem>
  </ItemGroup>
  <ItemGroup>
    <MainItem>
      <Key>Davies</Key>
      <Forenames>H. N.</Forenames>
      <Text>..:</Text>
      <PageNumber>5608</PageNumber>
    </MainItem>
  </ItemGroup>
  <ItemGroup>
    <MainItem>
      <Key>Dawson</Key>
      <Forenames>F. D.</Forenames>
      <PageNumber>4840</PageNumber>
    </MainItem>
  </ItemGroup>
  <ItemGroup>
    <MainItem>
      <Key>
        <KeyDitto>___ ___ ___ ___</KeyDitto>
      </Key>
      <Text>Q Q</Text>
      <PageNumber>4240</PageNumber>
    </MainItem>
  </ItemGroup>
  <ItemGroup>
    <MainItem>
      <Key>Deighton</Key>
      <Forenames>D. M .</Forenames>
      <PageNumber>6003</PageNumber>
    </MainItem>
  </ItemGroup>
  <ItemGroup>
    <MainItem>
      <Key>Dennis</Key>
      <Forenames>G. M.</Forenames>
      <PageNumber>5180</PageNumber>
    </MainItem>
  </ItemGroup>
  <ItemGroup>
    <MainItem>
      <Key>
        <KeyDitto>___ ___ —___ ___</KeyDitto>
      </Key>
      <Forenames>S. D .</Forenames>
      <PageNumber>4240</PageNumber>
    </MainItem>
  </ItemGroup>
  <ItemGroup>
    <MainItem>
      <Key>Dickson</Key>
      <Forenames>D.</Forenames>
      <PageNumber>4648</PageNumber>
    </MainItem>
  </ItemGroup>
  <ItemGroup>
    <MainItem>
      <Key>Dipple</Key>
      <Forenames>W. E .</Forenames>
      <PageNumber>4240</PageNumber>
    </MainItem>
  </ItemGroup>
  <ItemGroup>
    <MainItem>
      <Key>Donkin</Key>
      <Forenames>R. H .</Forenames>
      <PageNumber>5608</PageNumber>
    </MainItem>
  </ItemGroup>
  <ItemGroup>
    <MainItem>
      <Key>Douglas-Hamilton</Key>
      <Forenames>D.</Forenames>
      <Text>, Marquess of Douglas arid Clydesdale</Text>
      <PageNumber>4649</PageNumber>
    </MainItem>
  </ItemGroup>
  <ItemGroup>
    <MainItem>
      <Key>Drummond</Key>
      <Forenames>E. M.</Forenames>
      <PageNumber>5608</PageNumber>
    </MainItem>
  </ItemGroup>
  <ItemGroup>
    <MainItem>
      <Key>
        <KeyDitto>___ ___ ___ ___</KeyDitto>
      </Key>
      <Forenames>Peter</Forenames>
      <PageNumber>5678</PageNumber>
    </MainItem>
  </ItemGroup>
  <ItemGroup>
    <MainItem>
      <Key>
        <KeyDitto>___ ___ ___ ___ ___</KeyDitto>
      </Key>
      <Forenames>R. M.</Forenames>
      <PageNumber>6003</PageNumber>
    </MainItem>
  </ItemGroup>
  <ItemGroup>
    <MainItem>
      <Key>Du</Key>
      <Forenames>Boulay</Forenames>
      <Text>,-G. G. H</Text>
      <PageNumber>4240</PageNumber>
    </MainItem>
  </ItemGroup>
  <ItemGroup>
    <MainItem>
      <Key>Du</Key>
      <Forenames>Heaume</Forenames>
      <Text>, E. H</Text>
      <PageNumber>4497</PageNumber>
    </MainItem>
  </ItemGroup>
  <ItemGroup>
    <MainItem>
      <Key>Dudding</Key>
      <Forenames>M. C .</Forenames>
      <PageNumber>4649</PageNumber>
    </MainItem>
  </ItemGroup>
  <ItemGroup>
    <MainItem>
      <Key>Duff</Key>
      <Forenames>J. F .</Forenames>
      <PageNumber>6003</PageNumber>
    </MainItem>
  </ItemGroup>
  <ItemGroup>
    <MainItem>
      <Key>Duffey</Key>
      <Forenames>H. W .</Forenames>
      <PageNumber>4648</PageNumber>
    </MainItem>
  </ItemGroup>
  <ItemGroup>
    <MainItem>
      <Key>Duffield</Key>
      <Forenames>E. I. T.</Forenames>
      <PageNumber>4240</PageNumber>
    </MainItem>
  </ItemGroup>
  <ItemGroup>
    <MainItem>
      <Key>Duguid</Key>
      <Forenames>A.</Forenames>
      <PageNumber>4649</PageNumber>
    </MainItem>
  </ItemGroup>
  <ItemGroup>
    <MainItem>
      <Key>Dunne</Key>
      <Forenames>F. J .</Forenames>
      <PageNumber>4648</PageNumber>
    </MainItem>
  </ItemGroup>
  <ItemGroup>
    <MainItem>
      <Key>Dunning</Key>
      <Forenames>R. W. F.</Forenames>
      <PageNumber>4648</PageNumber>
    </MainItem>
  </ItemGroup>
  <ItemGroup>
    <MainItem>
      <Key>Dyas</Key>
      <Forenames>M. V.</Forenames>
      <PageNumber>4240</PageNumber>
    </MainItem>
  </ItemGroup>
  <ItemGroup>
    <MainItem>
      <Key>Eades</Key>
      <Forenames>F. T.</Forenames>
      <PageNumber>4649</PageNumber>
    </MainItem>
  </ItemGroup>
  <ItemGroup>
    <MainItem>
      <Key>Eagleson</Key>
      <Forenames>H. J.</Forenames>
      <PageNumber>6128</PageNumber>
    </MainItem>
  </ItemGroup>
  <ItemGroup>
    <MainItem>
      <Key>Edwards</Key>
      <Forenames>J. A.</Forenames>
      <PageNumber>4841</PageNumber>
    </MainItem>
  </ItemGroup>
  <ItemGroup>
    <MainItem>
      <Key>
        <KeyDitto>___ ___ .</KeyDitto>
      </Key>
      <Forenames>R. C.</Forenames>
      <PageNumber>5180</PageNumber>
    </MainItem>
  </ItemGroup>
  <ItemGroup>
    <MainItem>
      <Key>Elliot</Key>
      <Forenames>G. A .</Forenames>
      <PageNumber>4328</PageNumber>
    </MainItem>
  </ItemGroup>
  <ItemGroup>
    <MainItem>
      <Key>Elliott</Key>
      <Forenames>E. F .</Forenames>
      <PageNumber>4240</PageNumber>
    </MainItem>
  </ItemGroup>
  <ItemGroup>
    <MainItem>
      <Key>Ely</Key>
      <Forenames>M. H .</Forenames>
      <PageNumber>4240</PageNumber>
    </MainItem>
  </ItemGroup>
  <ItemGroup>
    <MainItem>
      <Key>Embry</Key>
      <Forenames>B. E .</Forenames>
      <PageNumber>5608</PageNumber>
    </MainItem>
  </ItemGroup>
  <ItemGroup>
    <MainItem>
      <Key>Evans</Key>
      <Forenames>C. H. L .</Forenames>
      <PageNumber>4497</PageNumber>
    </MainItem>
  </ItemGroup>
  <ItemGroup>
    <MainItem>
      <Key>Eyre</Key>
      <Forenames>V. O .</Forenames>
      <PageNumber>4840</PageNumber>
    </MainItem>
  </ItemGroup>
  <ItemGroup>
    <MainItem>
      <Key>Fachiri</Key>
      <Forenames>G.</Forenames>
      <PageNumber>6128</PageNumber>
    </MainItem>
  </ItemGroup>
  <ItemGroup>
    <MainItem>
      <Key>Fairhead</Key>
      <Forenames>F. G .</Forenames>
      <PageNumber>5336</PageNumber>
    </MainItem>
  </ItemGroup>
  <ItemGroup>
    <MainItem>
      <Key>Falconar</Key>
      <Forenames>G. B .</Forenames>
      <PageNumber>4240</PageNumber>
    </MainItem>
  </ItemGroup>
  <ItemGroup>
    <MainItem>
      <Key>Falkner</Key>
      <Text>II. E</Text>
      <PageNumber>4328</PageNumber>
    </MainItem>
  </ItemGroup>
  <ItemGroup>
    <MainItem>
      <Key>Fawssett</Key>
      <Forenames>F. A. B.</Forenames>
      <PageNumber>4840</PageNumber>
    </MainItem>
  </ItemGroup>
  <ItemGroup>
    <MainItem>
      <Key>Feasey</Key>
      <Forenames>C. E. V.</Forenames>
      <Text>LE</Text>
      <PageNumber>5181</PageNumber>
    </MainItem>
  </ItemGroup>
  <ItemGroup>
    <MainItem>
      <Key>Featherstone</Key>
      <Forenames>W. A. E.</Forenames>
      <PageNumber>4240</PageNumber>
    </MainItem>
  </ItemGroup>
  <ItemGroup>
    <MainItem>
      <Key>Fernihough</Key>
      <Forenames>F.</Forenames>
      <PageNumber>4649</PageNumber>
    </MainItem>
  </ItemGroup>
  <ItemGroup>
    <MainItem>
      <Key>Ferrell</Key>
      <Forenames>C. G .</Forenames>
      <PageNumber>4648</PageNumber>
    </MainItem>
  </ItemGroup>
  <ItemGroup>
    <MainItem>
      <Key>Ferrier</Key>
      <Forenames>F. G.</Forenames>
      <PageNumber>4240</PageNumber>
    </MainItem>
  </ItemGroup>
  <ItemGroup>
    <MainItem>
      <Key>Ffoulkes-Jones</Key>
      <Forenames>E. J.</Forenames>
      <PageNumber>5873</PageNumber>
    </MainItem>
    <KeyDitto>___ ___ ___ ___ ___</KeyDitto>
    <SubItem>
      <Text>R. M</Text>
      <PageNumber>4497</PageNumber>
    </SubItem>
  </ItemGroup>
  <ItemGroup>
    <MainItem>
      <Key>Finzel</Key>
      <Forenames>F. E. C.</Forenames>
      <PageNumber>4648</PageNumber>
    </MainItem>
  </ItemGroup>
  <ItemGroup>
    <MainItem>
      <Key>Fitzpatrick</Key>
      <Forenames>D. G. P.</Forenames>
      <PageNumber>5608</PageNumber>
    </MainItem>
  </ItemGroup>
  <ItemGroup>
    <MainItem>
      <Key>Fleming</Key>
      <Forenames>R. S .</Forenames>
      <PageNumber>4841</PageNumber>
    </MainItem>
  </ItemGroup>
  <ItemGroup>
    <MainItem>
      <Key>Foote</Key>
      <Forenames>H. W .</Forenames>
      <PageNumber>4841</PageNumber>
    </MainItem>
  </ItemGroup>
  <ItemGroup>
    <MainItem>
      <Key>Forbes</Key>
      <Forenames>H. V .</Forenames>
      <PageNumber>4497</PageNumber>
    </MainItem>
  </ItemGroup>
  <ItemGroup>
    <MainItem>
      <Key>Forrest</Key>
      <Forenames>H.</Forenames>
      <PageNumber>4241</PageNumber>
    </MainItem>
    <KeyDitto>___ ___</KeyDitto>
    <KeyDitto>___ ___ ...</KeyDitto>
    <KeyDitto>___ ___ ...</KeyDitto>
    <SubItem>
      <Text>K. D</Text>
      <PageNumber>5336</PageNumber>
    </SubItem>
  </ItemGroup>
  <ItemGroup>
    <MainItem>
      <Key>Fo</Key>
      <Text>ulerton, A. B. B</Text>
      <PageNumber>4497</PageNumber>
    </MainItem>
  </ItemGroup>
  <ItemGroup>
    <MainItem>
      <Key>Fbxen</Key>
      <Forenames>H. T .</Forenames>
      <PageNumber>5336</PageNumber>
    </MainItem>
  </ItemGroup>
  <ItemGroup>
    <MainItem>
      <Key>Fraser</Key>
      <Forenames>H. P .</Forenames>
      <PageNumber>4649</PageNumber>
    </MainItem>
  </ItemGroup>
  <ItemGroup>
    <MainItem>
      <Key>Fremantle</Key>
      <Forenames>D. R.</Forenames>
      <PageNumber>4240</PageNumber>
    </MainItem>
  </ItemGroup>
  <ItemGroup>
    <MainItem>
      <Key>French</Key>
      <Forenames>T. H .</Forenames>
      <PageNumber>4648</PageNumber>
    </MainItem>
  </ItemGroup>
  <ItemGroup>
    <MainItem>
      <Key>Fresson</Key>
      <Forenames>N. H .</Forenames>
      <PageNumber>4240</PageNumber>
    </MainItem>
  </ItemGroup>
  <ItemGroup>
    <MainItem>
      <Key>Frew</Key>
      <Forenames>M. B .</Forenames>
      <PageNumber>4328</PageNumber>
    </MainItem>
  </ItemGroup>
  <ItemGroup>
    <MainItem>
      <Key>Gardiner</Key>
      <Forenames>P. G. S.</Forenames>
      <PageNumber>5181</PageNumber>
    </MainItem>
  </ItemGroup>
  <ItemGroup>
    <MainItem>
      <Key>Gauntlett</Key>
      <Forenames>F. V.</Forenames>
      <PageNumber>5335</PageNumber>
    </MainItem>
  </ItemGroup>
  <ItemGroup>
    <MainItem>
      <Key>Gillan</Key>
      <Forenames>J. W .</Forenames>
      <Text>,</Text>
      <PageNumber>5001</PageNumber>
    </MainItem>
  </ItemGroup>
  <ItemGroup>
    <MainItem>
      <Key>Glen</Key>
      <Forenames>J. A.</Forenames>
      <PageNumber>4841</PageNumber>
      <PageNumber>4841</PageNumber>
    </MainItem>
  </ItemGroup>
  <KeyDitto>___ ___ ...</KeyDitto>
  <ItemGroup>
    <MainItem>
      <Key>Gower-Jones</Key>
      <Forenames>F.</Forenames>
      <PageNumber>5608</PageNumber>
    </MainItem>
  </ItemGroup>
  <ItemGroup>
    <MainItem>
      <Key>Grannum</Key>
      <Forenames>O. W.</Forenames>
      <PageNumber>5608</PageNumber>
    </MainItem>
  </ItemGroup>
  <ItemGroup>
    <MainItem>
      <Key>Gray</Key>
      <Forenames>L. G.</Forenames>
      <PageNumber>4328</PageNumber>
    </MainItem>
  </ItemGroup>
  <ItemGroup>
    <MainItem>
      <Key>
        <KeyDitto>___ ___</KeyDitto>
      </Key>
      <Forenames>S. H. C .</Forenames>
      <PageNumber>5608</PageNumber>
    </MainItem>
  </ItemGroup>
  <ItemGroup>
    <MainItem>
      <Key>Green</Key>
      <Forenames>R. L.</Forenames>
      <PageNumber>5180</PageNumber>
    </MainItem>
  </ItemGroup>
  <ItemGroup>
    <MainItem>
      <Key>Greene</Key>
      <Forenames>F. C. B.</Forenames>
      <PageNumber>4841</PageNumber>
    </MainItem>
  </ItemGroup>
  <ItemGroup>
    <MainItem>
      <Key>Greenhalgh</Key>
      <Forenames>R. C.</Forenames>
      <PageNumber>6128</PageNumber>
    </MainItem>
  </ItemGroup>
  <ItemGroup>
    <MainItem>
      <Key>Greenshields</Key>
      <Forenames>J. A.</Forenames>
      <PageNumber>4840</PageNumber>
    </MainItem>
  </ItemGroup>
  <ItemGroup>
    <MainItem>
      <Key>Grenfell</Key>
      <Forenames>A. R.</Forenames>
      <PageNumber>5608</PageNumber>
    </MainItem>
  </ItemGroup>
  <ItemGroup>
    <MainItem>
      <Key>Grierson</Key>
      <Forenames>C.</Forenames>
      <Text>McK</Text>
      <PageNumber>5180</PageNumber>
    </MainItem>
  </ItemGroup>
  <ItemGroup>
    <MainItem>
      <Key>Griffith</Key>
      <Forenames>R. H .</Forenames>
      <PageNumber>5873</PageNumber>
    </MainItem>
  </ItemGroup>
  <ItemGroup>
    <MainItem>
      <Key>Griffiths</Key>
      <Forenames>E. W .</Forenames>
      <PageNumber>4328</PageNumber>
    </MainItem>
  </ItemGroup>
  <KeyDitto>___ ___</KeyDitto>
  <ItemGroup>
    <MainItem>
      <Key>Guilfoyle</Key>
      <Forenames>W. J. Y.</Forenames>
      <PageNumber>6003</PageNumber>
    </MainItem>
  </ItemGroup>
  <ItemGroup>
    <MainItem>
      <Key>Guvler</Key>
      <Forenames>W. D .</Forenames>
      <PageNumber>4240</PageNumber>
    </MainItem>
  </ItemGroup>
  <ItemGroup>
    <MainItem>
      <Key>Hadley</Key>
      <Forenames>G. A .</Forenames>
      <PageNumber>5872</PageNumber>
    </MainItem>
  </ItemGroup>
  <ItemGroup>
    <MainItem>
      <Key>Hale</Key>
      <Forenames>A. W. B.</Forenames>
      <PageNumber>5001</PageNumber>
    </MainItem>
  </ItemGroup>
  <ItemGroup>
    <MainItem>
      <Key>Hall</Key>
      <Forenames>F. M .</Forenames>
      <PageNumber>5609</PageNumber>
    </MainItem>
  </ItemGroup>
  <ItemGroup>
    <MainItem>
      <Key>Hampson</Key>
      <Forenames>H. B.</Forenames>
      <PageNumber>4328</PageNumber>
    </MainItem>
  </ItemGroup>
  <ItemGroup>
    <MainItem>
      <Key>Hardman</Key>
      <Forenames>E. P.</Forenames>
      <PageNumber>4240</PageNumber>
    </MainItem>
  </ItemGroup>
  <ItemGroup>
    <MainItem>
      <Key>
        <KeyDitto>___ ___ ___</KeyDitto>
      </Key>
      <Forenames>J. D. I</Forenames>
      <Text>Hargroves, J. H</Text>
      <PageNumber>4240</PageNumber>
      <PageNumber>5335</PageNumber>
    </MainItem>
  </ItemGroup>
  <KeyDitto>___ ___ ___</KeyDitto>
</Index>

